Workbook

Sheet Executive Dashboard
A1: SWISH 10-MIN DELIVERY — BANGALORE ZONE OPERATIONS DASHBOARD
A2: Executive control center — all figures update automatically from the underlying trackers.
A3: Report Date: | B3: =MAX('Daily Order Tracker'!$A$4:$A$93) -> 46282
A5: =COUNTIFS('Daily Order Tracker'!$A$4:$A$93,$B$3) -> 30 | C5: =COUNTIFS('Daily Order Tracker'!$A$4:$A$93,$B$3,'Daily Order Tracker'!$N$4:$N$93,"Delivered") -> 17 | E5: =COUNTIFS('Daily Order Tracker'!$A$4:$A$93,$B$3,'Daily Order Tracker'!$N$4:$N$93,"<>Delivered",'Daily Order Tracker'!$N$4:$N$93,"<>Cancelled") -> 8 | G5: =COUNTIF('Daily Order Tracker'!$N$4:$N$93,"Cancelled") -> 10 | I5: =SUMIFS('Daily Order Tracker'!$P$4:$P$93,'Daily Order Tracker'!$N$4:$N$93,"Delivered") -> 29595 | K5: =IFERROR(COUNTIFS('Daily Order Tracker'!$N$4:$N$93,"Delivered",'Daily Order Tracker'!$M$4:$M$93,"<=10")/COUNTIF('Daily Order Tracker'!$N$4:$N$93,"Delivered"),0) -> 0.25
A8: TODAY'S ORDERS | C8: COMPLETED DELIVERIES | E8: ACTIVE ORDERS | G8: CANCELLED ORDERS | I8: REVENUE (3-DAY) | K8: ON-TIME DELIVERY %
A10: =IFERROR(AVERAGEIFS('Daily Order Tracker'!$M$4:$M$93,'Daily Order Tracker'!$M$4:$M$93,"<>"),0) -> 11.875 | C10: =IFERROR(AVERAGEIFS('Daily Order Tracker'!$Q$4:$Q$93,'Daily Order Tracker'!$Q$4:$Q$93,"<>"),0) -> 5.96 | E10: =AVERAGE('Rider Performance Tracker'!$F$4:$F$23)/20 -> 0.18 | G10: =IFERROR(AVERAGEIFS('Daily Order Tracker'!$P$4:$P$93,'Daily Order Tracker'!$N$4:$N$93,"Delivered"),0) -> 411.04167 | I10: =COUNTA('Rider Performance Tracker'!$A$4:$A$23) -> 20 | K10: =COUNTIFS('Customer Complaints'!$F$4:$F$18,"<>Resolved") -> 8
A13: AVG DELIVERY TIME (min) | C13: AVG KITCHEN PREP TIME (min) | E13: RIDER UTILIZATION | G13: AVG ORDER VALUE | I13: ACTIVE RIDERS | K13: OPEN COMPLAINTS
A15: ZONE-WISE PERFORMANCE | G15: KITCHEN LOAD HEATMAP (orders by time block)
A16: Zone | B16: Orders | C16: Revenue (₹) | D16: Avg Delivery (min) | E16: Cancel Rate | G16: Kitchen | H16: 0-3 | I16: 4-7 | J16: 8-11 | K16: 12-15 | L16: 16-19
A17: ='Zone Performance'!A4 -> Koramangala | B17: ='Zone Performance'!B4 -> 9 | C17: ='Zone Performance'!C4 -> 3300 | D17: ='Zone Performance'!D4 -> 10.75 | E17: ='Zone Performance'!H4 -> 0 | G17: =Hourly_Helper!A2 -> Swish Kitchen - Koramangala | H17: =Hourly_Helper!AA2 -> 0 | I17: =Hourly_Helper!AB2 -> 0 | J17: =Hourly_Helper!AC2 -> 2 | K17: =Hourly_Helper!AD2 -> 2 | L17: =Hourly_Helper!AE2 -> 3
A18: ='Zone Performance'!A5 -> HSR Layout | B18: ='Zone Performance'!B5 -> 9 | C18: ='Zone Performance'!C5 -> 3262 | D18: ='Zone Performance'!D5 -> 11.857143 | E18: ='Zone Performance'!H5 -> 0.11111111 | G18: =Hourly_Helper!A3 -> Swish Kitchen - HSR Layout | H18: =Hourly_Helper!AA3 -> 0 | I18: =Hourly_Helper!AB3 -> 0 | J18: =Hourly_Helper!AC3 -> 3 | K18: =Hourly_Helper!AD3 -> 2 | L18: =Hourly_Helper!AE3 -> 2
A19: ='Zone Performance'!A6 -> Indiranagar | B19: ='Zone Performance'!B6 -> 9 | C19: ='Zone Performance'!C6 -> 3017 | D19: ='Zone Performance'!D6 -> 12.285714 | E19: ='Zone Performance'!H6 -> 0.22222222 | G19: =Hourly_Helper!A4 -> Swish Kitchen - Indiranagar | H19: =Hourly_Helper!AA4 -> 0 | I19: =Hourly_Helper!AB4 -> 0 | J19: =Hourly_Helper!AC4 -> 2 | K19: =Hourly_Helper!AD4 -> 1 | L19: =Hourly_Helper!AE4 -> 6
A20: ='Zone Performance'!A7 -> Whitefield | B20: ='Zone Performance'!B7 -> 9 | C20: ='Zone Performance'!C7 -> 2851 | D20: ='Zone Performance'!D7 -> 11.857143 | E20: ='Zone Performance'!H7 -> 0.22222222 | G20: =Hourly_Helper!A5 -> Swish Kitchen - Whitefield | H20: =Hourly_Helper!AA5 -> 0 | I20: =Hourly_Helper!AB5 -> 0 | J20: =Hourly_Helper!AC5 -> 4 | K20: =Hourly_Helper!AD5 -> 2 | L20: =Hourly_Helper!AE5 -> 2
A21: ='Zone Performance'!A8 -> Electronic City | B21: ='Zone Performance'!B8 -> 9 | C21: ='Zone Performance'!C8 -> 3082 | D21: ='Zone Performance'!D8 -> 13 | E21: ='Zone Performance'!H8 -> 0 | G21: =Hourly_Helper!A6 -> Swish Kitchen - Electronic City | H21: =Hourly_Helper!AA6 -> 0 | I21: =Hourly_Helper!AB6 -> 0 | J21: =Hourly_Helper!AC6 -> 4 | K21: =Hourly_Helper!AD6 -> 3 | L21: =Hourly_Helper!AE6 -> 1
A22: ='Zone Performance'!A9 -> Marathahalli | B22: ='Zone Performance'!B9 -> 9 | C22: ='Zone Performance'!C9 -> 2095 | D22: ='Zone Performance'!D9 -> 10.6 | E22: ='Zone Performance'!H9 -> 0.33333333 | G22: =Hourly_Helper!A7 -> Swish Kitchen - Marathahalli | H22: =Hourly_Helper!AA7 -> 0 | I22: =Hourly_Helper!AB7 -> 0 | J22: =Hourly_Helper!AC7 -> 3 | K22: =Hourly_Helper!AD7 -> 1 | L22: =Hourly_Helper!AE7 -> 4
A23: ='Zone Performance'!A10 -> JP Nagar | B23: ='Zone Performance'!B10 -> 9 | C23: ='Zone Performance'!C10 -> 2651 | D23: ='Zone Performance'!D10 -> 12.142857 | E23: ='Zone Performance'!H10 -> 0.11111111 | G23: =Hourly_Helper!A8 -> Swish Kitchen - JP Nagar | H23: =Hourly_Helper!AA8 -> 0 | I23: =Hourly_Helper!AB8 -> 0 | J23: =Hourly_Helper!AC8 -> 1 | K23: =Hourly_Helper!AD8 -> 4 | L23: =Hourly_Helper!AE8 -> 3
A24: ='Zone Performance'!A11 -> BTM Layout | B24: ='Zone Performance'!B11 -> 9 | C24: ='Zone Performance'!C11 -> 3148 | D24: ='Zone Performance'!D11 -> 13 | E24: ='Zone Performance'!H11 -> 0 | G24: =Hourly_Helper!A9 -> Swish Kitchen - BTM Layout | H24: =Hourly_Helper!AA9 -> 0 | I24: =Hourly_Helper!AB9 -> 0 | J24: =Hourly_Helper!AC9 -> 3 | K24: =Hourly_Helper!AD9 -> 1 | L24: =Hourly_Helper!AE9 -> 2
A25: ='Zone Performance'!A12 -> Bellandur | B25: ='Zone Performance'!B12 -> 9 | C25: ='Zone Performance'!C12 -> 3542 | D25: ='Zone Performance'!D12 -> 11.125 | E25: ='Zone Performance'!H12 -> 0 | G25: =Hourly_Helper!A10 -> Swish Kitchen - Bellandur | H25: =Hourly_Helper!AA10 -> 0 | I25: =Hourly_Helper!AB10 -> 0 | J25: =Hourly_Helper!AC10 -> 2 | K25: =Hourly_Helper!AD10 -> 1 | L25: =Hourly_Helper!AE10 -> 5
A26: ='Zone Performance'!A13 -> Sarjapur | B26: ='Zone Performance'!B13 -> 9 | C26: ='Zone Performance'!C13 -> 2647 | D26: ='Zone Performance'!D13 -> 11.714286 | E26: ='Zone Performance'!H13 -> 0.11111111 | G26: =Hourly_Helper!A11 -> Swish Kitchen - Sarjapur | H26: =Hourly_Helper!AA11 -> 0 | I26: =Hourly_Helper!AB11 -> 0 | J26: =Hourly_Helper!AC11 -> 2 | K26: =Hourly_Helper!AD11 -> 2 | L26: =Hourly_Helper!AE11 -> 3
A28: HOURLY ORDER TREND | G28: ZONE-WISE REVENUE

Sheet Daily Order Tracker
A1: DAILY ORDER TRACKER — Swish 10-Min Delivery (Bangalore Zone)
A2: Live order-level log. Grey helper columns (Q-S) power all analytics on other sheets — do not delete.
A3: Date | B3: Order ID | C3: Customer Name | D3: Phone | E3: Zone | F3: Kitchen | G3: Rider Assigned | H3: Order Time | I3: Preparation Start | J3: Preparation End | K3: Pickup Time | L3: Delivery Time | M3: Total Delivery Minutes | N3: Status | O3: Delay Reason | P3: Order Value | Q3: Prep Minutes (calc) | R3: Order Hour (calc) | S3: Delay Flag (calc)
A4: 46280 | B4: ORD1001 | C4: Ved Trivedi | D4: 9104332181 | E4: Koramangala | F4: Swish Kitchen - Koramangala | G4: R001 | H4: 0.72708333 | I4: 0.72708333 | J4: 0.72916667 | K4: 0.72916667 | L4: 0.73125 | M4: =IF(N4="Delivered",IFERROR((L4-H4)*1440,""),"") -> 6 | N4: Delivered | P4: 358 | Q4: =IF(AND(I4<>"",J4<>""),(J4-I4)*1440,"") -> 3 | R4: =IF(H4<>"",HOUR(H4),"") -> 17 | S4: =IF(AND(N4="Delivered",M4<>"",M4>10),"Y","N") -> N
A5: 46280 | B5: ORD1002 | C5: Aarav Shah | D5: 9838637940 | E5: HSR Layout | F5: Swish Kitchen - HSR Layout | G5: R004 | H5: 0.86875 | I5: 0.86875 | J5: 0.87430556 | K5: 0.875 | L5: 0.87777778 | M5: =IF(N5="Delivered",IFERROR((L5-H5)*1440,""),"") -> 13 | N5: Delivered | O5: Peak hour surge | P5: 404 | Q5: =IF(AND(I5<>"",J5<>""),(J5-I5)*1440,"") -> 8 | R5: =IF(H5<>"",HOUR(H5),"") -> 20 | S5: =IF(AND(N5="Delivered",M5<>"",M5>10),"Y","N") -> Y
A6: 46280 | B6: ORD1003 | C6: Arnav Sinha | D6: 9116155940 | E6: Indiranagar | F6: Swish Kitchen - Indiranagar | G6: R005 | H6: 0.81180556 | I6: 0.81180556 | J6: 0.81597222 | K6: 0.81597222 | L6: 0.82013889 | M6: =IF(N6="Delivered",IFERROR((L6-H6)*1440,""),"") -> 12 | N6: Delivered | O6: Address not found | P6: 420 | Q6: =IF(AND(I6<>"",J6<>""),(J6-I6)*1440,"") -> 6 | R6: =IF(H6<>"",HOUR(H6),"") -> 19 | S6: =IF(AND(N6="Delivered",M6<>"",M6>10),"Y","N") -> Y
A7: 46280 | B7: ORD1004 | C7: Reyan Dutta | D7: 9593103413 | E7: Whitefield | F7: Swish Kitchen - Whitefield | G7: R008 | H7: 0.87916667 | I7: 0.87986111 | J7: 0.88333333 | K7: 0.88402778 | L7: 0.88888889 | M7: =IF(N7="Delivered",IFERROR((L7-H7)*1440,""),"") -> 14 | N7: Delivered | O7: Heavy traffic | P7: 493 | Q7: =IF(AND(I7<>"",J7<>""),(J7-I7)*1440,"") -> 5 | R7: =IF(H7<>"",HOUR(H7),"") -> 21 | S7: =IF(AND(N7="Delivered",M7<>"",M7>10),"Y","N") -> Y
A8: 46280 | B8: ORD1005 | C8: Reyansh Jain | D8: 9419283276 | E8: Electronic City | F8: Swish Kitchen - Electronic City | G8: R009 | H8: 0.54097222 | I8: 0.54097222 | J8: 0.54652778 | K8: 0.54722222 | L8: 0.54861111 | M8: =IF(N8="Delivered",IFERROR((L8-H8)*1440,""),"") -> 11 | N8: Delivered | O8: Peak hour surge | P8: 354 | Q8: =IF(AND(I8<>"",J8<>""),(J8-I8)*1440,"") -> 8 | R8: =IF(H8<>"",HOUR(H8),"") -> 12 | S8: =IF(AND(N8="Delivered",M8<>"",M8>10),"Y","N") -> Y
A9: 46280 | B9: ORD1006 | C9: Arnav Sinha | D9: 9641395376 | E9: Marathahalli | F9: Swish Kitchen - Marathahalli | G9: R012 | H9: 0.77013889 | I9: 0.77013889 | J9: 0.77361111 | K9: 0.77361111 | L9: 0.77569444 | M9: =IF(N9="Delivered",IFERROR((L9-H9)*1440,""),"") -> 8 | N9: Delivered | P9: 389 | Q9: =IF(AND(I9<>"",J9<>""),(J9-I9)*1440,"") -> 5 | R9: =IF(H9<>"",HOUR(H9),"") -> 18 | S9: =IF(AND(N9="Delivered",M9<>"",M9>10),"Y","N") -> N
A10: 46280 | B10: ORD1007 | C10: Navya Desai | D10: 9965328710 | E10: JP Nagar | F10: Swish Kitchen - JP Nagar | G10: R013 | H10: 0.87986111 | I10: 0.87986111 | J10: 0.88541667 | K10: 0.88541667 | L10: 0.89027778 | M10: =IF(N10="Delivered",IFERROR((L10-H10)*1440,""),"") -> 15 | N10: Delivered | O10: High order volume | P10: 552 | Q10: =IF(AND(I10<>"",J10<>""),(J10-I10)*1440,"") -> 8 | R10: =IF(H10<>"",HOUR(H10),"") -> 21 | S10: =IF(AND(N10="Delivered",M10<>"",M10>10),"Y","N") -> Y
A11: 46280 | B11: ORD1008 | C11: Kian Fernandes | D11: 9978480184 | E11: BTM Layout | F11: Swish Kitchen - BTM Layout | G11: R016 | H11: 0.86180556 | I11: 0.8625 | J11: 0.86458333 | K11: 0.86527778 | L11: 0.86875 | M11: =IF(N11="Delivered",IFERROR((L11-H11)*1440,""),"") -> 10 | N11: Delivered | P11: 281 | Q11: =IF(AND(I11<>"",J11<>""),(J11-I11)*1440,"") -> 3 | R11: =IF(H11<>"",HOUR(H11),"") -> 20 | S11: =IF(AND(N11="Delivered",M11<>"",M11>10),"Y","N") -> N
A12: 46280 | B12: ORD1009 | C12: Ira Sharma | D12: 9482814893 | E12: Bellandur | F12: Swish Kitchen - Bellandur | G12: R017 | H12: 0.43263889 | I12: 0.43263889 | J12: 0.4375 | K12: 0.43888889 | L12: 0.44027778 | M12: =IF(N12="Delivered",IFERROR((L12-H12)*1440,""),"") -> 11 | N12: Delivered | O12: Rider unavailable at pickup | P12: 451 | Q12: =IF(AND(I12<>"",J12<>""),(J12-I12)*1440,"") -> 7 | R12: =IF(H12<>"",HOUR(H12),"") -> 10 | S12: =IF(AND(N12="Delivered",M12<>"",M12>10),"Y","N") -> Y
A13: 46280 | B13: ORD1010 | C13: Pihu Agarwal | D13: 9543039117 | E13: Sarjapur | F13: Swish Kitchen - Sarjapur | G13: R020 | H13: 0.87777778 | I13: 0.87777778 | J13: 0.88055556 | K13: 0.88194444 | L13: 0.88541667 | M13: =IF(N13="Delivered",IFERROR((L13-H13)*1440,""),"") -> 11 | N13: Delivered | O13: Peak hour surge | P13: 289 | Q13: =IF(AND(I13<>"",J13<>""),(J13-I13)*1440,"") -> 4 | R13: =IF(H13<>"",HOUR(H13),"") -> 21 | S13: =IF(AND(N13="Delivered",M13<>"",M13>10),"Y","N") -> Y
A14: 46280 | B14: ORD1011 | C14: Sanya Bhatia | D14: 9638346578 | E14: Koramangala | F14: Swish Kitchen - Koramangala | G14: R001 | H14: 0.62986111 | I14: 0.62986111 | J14: 0.63263889 | K14: 0.63263889 | L14: 0.63541667 | M14: =IF(N14="Delivered",IFERROR((L14-H14)*1440,""),"") -> 8 | N14: Delivered | P14: 141 | Q14: =IF(AND(I14<>"",J14<>""),(J14-I14)*1440,"") -> 4 | R14: =IF(H14<>"",HOUR(H14),"") -> 15 | S14: =IF(AND(N14="Delivered",M14<>"",M14>10),"Y","N") -> N
A15: 46280 | B15: ORD1012 | C15: Myra Kapoor | D15: 9930103105 | E15: HSR Layout | F15: Swish Kitchen - HSR Layout | G15: R004 | H15: 0.39722222 | I15: 0.39722222 | J15: 0.40069444 | K15: 0.40208333 | L15: 0.40555556 | M15: =IF(N15="Delivered",IFERROR((L15-H15)*1440,""),"") -> 12 | N15: Delivered | O15: Rider took wrong route | P15: 339 | Q15: =IF(AND(I15<>"",J15<>""),(J15-I15)*1440,"") -> 5 | R15: =IF(H15<>"",HOUR(H15),"") -> 9 | S15: =IF(AND(N15="Delivered",M15<>"",M15>10),"Y","N") -> Y
A16: 46280 | B16: ORD1013 | C16: Pihu Agarwal | D16: 9997376311 | E16: Indiranagar | F16: Swish Kitchen - Indiranagar | G16: R005 | H16: 0.76875 | I16: 0.76944444 | J16: 0.77361111 | K16: 0.77430556 | L16: 0.77777778 | M16: =IF(N16="Delivered",IFERROR((L16-H16)*1440,""),"") -> 13 | N16: Delivered | O16: Rider took wrong route | P16: 175 | Q16: =IF(AND(I16<>"",J16<>""),(J16-I16)*1440,"") -> 6 | R16: =IF(H16<>"",HOUR(H16),"") -> 18 | S16: =IF(AND(N16="Delivered",M16<>"",M16>10),"Y","N") -> Y
A17: 46280 | B17: ORD1014 | C17: Sara Khan | D17: 9065133387 | E17: Whitefield | F17: Swish Kitchen - Whitefield | G17: R008 | H17: 0.43541667 | I17: 0.43541667 | J17: 0.43888889 | K17: 0.43958333 | L17: 0.44166667 | M17: =IF(N17="Delivered",IFERROR((L17-H17)*1440,""),"") -> 9 | N17: Delivered | P17: 197 | Q17: =IF(AND(I17<>"",J17<>""),(J17-I17)*1440,"") -> 5 | R17: =IF(H17<>"",HOUR(H17),"") -> 10 | S17: =IF(AND(N17="Delivered",M17<>"",M17>10),"Y","N") -> N
A18: 46280 | B18: ORD1015 | C18: Kiara Vora | D18: 9810801326 | E18: Electronic City | F18: Swish Kitchen - Electronic City | G18: R009 | H18: 0.64583333 | I18: 0.64583333 | J18: 0.65208333 | K18: 0.65277778 | L18: 0.65416667 | M18: =IF(N18="Delivered",IFERROR((L18-H18)*1440,""),"") -> 12 | N18: Delivered | O18: High order volume | P18: 288 | Q18: =IF(AND(I18<>"",J18<>""),(J18-I18)*1440,"") -> 9 | R18: =IF(H18<>"",HOUR(H18),"") -> 15 | S18: =IF(AND(N18="Delivered",M18<>"",M18>10),"Y","N") -> Y
A19: 46280 | B19: ORD1016 | C19: Vivaan Chatterjee | D19: 9746872343 | E19: Marathahalli | F19: Swish Kitchen - Marathahalli | G19: R012 | H19: 0.35902778 | I19: 0.35902778 | J19: 0.36458333 | K19: 0.36527778 | L19: 0.36666667 | M19: =IF(N19="Delivered",IFERROR((L19-H19)*1440,""),"") -> 11 | N19: Delivered | O19: Address not found | P19: 171 | Q19: =IF(AND(I19<>"",J19<>""),(J19-I19)*1440,"") -> 8 | R19: =IF(H19<>"",HOUR(H19),"") -> 8 | S19: =IF(AND(N19="Delivered",M19<>"",M19>10),"Y","N") -> Y
A20: 46280 | B20: ORD1017 | C20: Pihu Agarwal | D20: 9820812191 | E20: JP Nagar | F20: Swish Kitchen - JP Nagar | G20: R013 | H20: 0.78819444 | I20: 0.78819444 | J20: 0.79236111 | K20: 0.79236111 | L20: 0.79652778 | M20: =IF(N20="Delivered",IFERROR((L20-H20)*1440,""),"") -> 12 | N20: Delivered | O20: Rider unavailable at pickup | P20: 372 | Q20: =IF(AND(I20<>"",J20<>""),(J20-I20)*1440,"") -> 6 | R20: =IF(H20<>"",HOUR(H20),"") -> 18 | S20: =IF(AND(N20="Delivered",M20<>"",M20>10),"Y","N") -> Y
A21: 46280 | B21: ORD1018 | C21: Sanya Bhatia | D21: 9169985435 | E21: BTM Layout | F21: Swish Kitchen - BTM Layout | G21: R016 | H21: 0.46944444 | I21: 0.47013889 | J21: 0.47291667 | K21: 0.47430556 | L21: 0.47916667 | M21: =IF(N21="Delivered",IFERROR((L21-H21)*1440,""),"") -> 14 | N21: Delivered | O21: Peak hour surge | P21: 427 | Q21: =IF(AND(I21<>"",J21<>""),(J21-I21)*1440,"") -> 4 | R21: =IF(H21<>"",HOUR(H21),"") -> 11 | S21: =IF(AND(N21="Delivered",M21<>"",M21>10),"Y","N") -> Y
A22: 46280 | B22: ORD1019 | C22: Pihu Agarwal | D22: 9107991183 | E22: Bellandur | F22: Swish Kitchen - Bellandur | G22: R017 | H22: 0.67777778 | I22: 0.67777778 | J22: 0.68125 | K22: 0.68125 | L22: 0.68333333 | M22: =IF(N22="Delivered",IFERROR((L22-H22)*1440,""),"") -> 8 | N22: Delivered | P22: 498 | Q22: =IF(AND(I22<>"",J22<>""),(J22-I22)*1440,"") -> 5 | R22: =IF(H22<>"",HOUR(H22),"") -> 16 | S22: =IF(AND(N22="Delivered",M22<>"",M22>10),"Y","N") -> N
A23: 46280 | B23: ORD1020 | C23: Dhruv Saxena | D23: 9849808412 | E23: Sarjapur | F23: Swish Kitchen - Sarjapur | G23: R020 | H23: 0.50486111 | I23: 0.50486111 | J23: 0.51041667 | K23: 0.51180556 | L23: 0.51388889 | M23: =IF(N23="Delivered",IFERROR((L23-H23)*1440,""),"") -> 13 | N23: Delivered | O23: Kitchen backlog | P23: 398 | Q23: =IF(AND(I23<>"",J23<>""),(J23-I23)*1440,"") -> 8 | R23: =IF(H23<>"",HOUR(H23),"") -> 12 | S23: =IF(AND(N23="Delivered",M23<>"",M23>10),"Y","N") -> Y
A24: 46280 | B24: ORD1021 | C24: Krish Choudhary | D24: 9534874016 | E24: Koramangala | F24: Swish Kitchen - Koramangala | G24: R001 | H24: 0.88680556 | I24: 0.88680556 | J24: 0.88888889 | K24: 0.88958333 | L24: 0.89166667 | M24: =IF(N24="Delivered",IFERROR((L24-H24)*1440,""),"") -> 7 | N24: Delivered | P24: 388 | Q24: =IF(AND(I24<>"",J24<>""),(J24-I24)*1440,"") -> 3 | R24: =IF(H24<>"",HOUR(H24),"") -> 21 | S24: =IF(AND(N24="Delivered",M24<>"",M24>10),"Y","N") -> N
A25: 46280 | B25: ORD1022 | C25: Dhruv Saxena | D25: 9868011280 | E25: HSR Layout | F25: Swish Kitchen - HSR Layout | G25: R004 | H25: 0.89097222 | I25: 0.89097222 | J25: 0.89513889 | K25: 0.89513889 | L25: 0.89652778 | M25: =IF(N25="Delivered",IFERROR((L25-H25)*1440,""),"") -> 8 | N25: Delivered | P25: 435 | Q25: =IF(AND(I25<>"",J25<>""),(J25-I25)*1440,"") -> 6 | R25: =IF(H25<>"",HOUR(H25),"") -> 21 | S25: =IF(AND(N25="Delivered",M25<>"",M25>10),"Y","N") -> N
A26: 46280 | B26: ORD1023 | C26: Pihu Agarwal | D26: 9053315869 | E26: Indiranagar | F26: Swish Kitchen - Indiranagar | G26: R005 | H26: 0.79791667 | M26: =IF(N26="Delivered",IFERROR((L26-H26)*1440,""),"") | N26: Cancelled | P26: 542 | Q26: =IF(AND(I26<>"",J26<>""),(J26-I26)*1440,"") | R26: =IF(H26<>"",HOUR(H26),"") -> 19 | S26: =IF(AND(N26="Delivered",M26<>"",M26>10),"Y","N") -> N
A27: 46280 | B27: ORD1024 | C27: Arnav Sinha | D27: 9634216073 | E27: Whitefield | F27: Swish Kitchen - Whitefield | G27: R008 | H27: 0.49444444 | I27: 0.49513889 | M27: =IF(N27="Delivered",IFERROR((L27-H27)*1440,""),"") | N27: Cancelled | P27: 348 | Q27: =IF(AND(I27<>"",J27<>""),(J27-I27)*1440,"") | R27: =IF(H27<>"",HOUR(H27),"") -> 11 | S27: =IF(AND(N27="Delivered",M27<>"",M27>10),"Y","N") -> N
A28: 46280 | B28: ORD1025 | C28: Arnav Sinha | D28: 9414586850 | E28: Electronic City | F28: Swish Kitchen - Electronic City | G28: R009 | H28: 0.41388889 | I28: 0.41458333 | J28: 0.41736111 | K28: 0.41875 | L28: 0.42152778 | M28: =IF(N28="Delivered",IFERROR((L28-H28)*1440,""),"") -> 11 | N28: Delivered | O28: High order volume | P28: 159 | Q28: =IF(AND(I28<>"",J28<>""),(J28-I28)*1440,"") -> 4 | R28: =IF(H28<>"",HOUR(H28),"") -> 9 | S28: =IF(AND(N28="Delivered",M28<>"",M28>10),"Y","N") -> Y
A29: 46280 | B29: ORD1026 | C29: Zara Ahmed | D29: 9569816934 | E29: Marathahalli | F29: Swish Kitchen - Marathahalli | G29: R012 | H29: 0.36458333 | I29: 0.36527778 | J29: 0.36736111 | K29: 0.36875 | L29: 0.37291667 | M29: =IF(N29="Delivered",IFERROR((L29-H29)*1440,""),"") -> 12 | N29: Delivered | O29: Rider unavailable at pickup | P29: 321 | Q29: =IF(AND(I29<>"",J29<>""),(J29-I29)*1440,"") -> 3 | R29: =IF(H29<>"",HOUR(H29),"") -> 8 | S29: =IF(AND(N29="Delivered",M29<>"",M29>10),"Y","N") -> Y
A30: 46280 | B30: ORD1027 | C30: Anaya Pillai | D30: 9595148465 | E30: JP Nagar | F30: Swish Kitchen - JP Nagar | G30: R013 | H30: 0.61388889 | I30: 0.61458333 | J30: 0.61944444 | K30: 0.61944444 | L30: 0.62152778 | M30: =IF(N30="Delivered",IFERROR((L30-H30)*1440,""),"") -> 11 | N30: Delivered | O30: High order volume | P30: 550 | Q30: =IF(AND(I30<>"",J30<>""),(J30-I30)*1440,"") -> 7 | R30: =IF(H30<>"",HOUR(H30),"") -> 14 | S30: =IF(AND(N30="Delivered",M30<>"",M30>10),"Y","N") -> Y
A31: 46280 | B31: ORD1028 | C31: Anaya Pillai | D31: 9299468044 | E31: BTM Layout | F31: Swish Kitchen - BTM Layout | G31: R016 | H31: 0.47708333 | I31: 0.47777778 | J31: 0.48194444 | K31: 0.48263889 | L31: 0.48611111 | M31: =IF(N31="Delivered",IFERROR((L31-H31)*1440,""),"") -> 13 | N31: Delivered | O31: Peak hour surge | P31: 338 | Q31: =IF(AND(I31<>"",J31<>""),(J31-I31)*1440,"") -> 6 | R31: =IF(H31<>"",HOUR(H31),"") -> 11 | S31: =IF(AND(N31="Delivered",M31<>"",M31>10),"Y","N") -> Y
A32: 46280 | B32: ORD1029 | C32: Reyan Dutta | D32: 9214895134 | E32: Bellandur | F32: Swish Kitchen - Bellandur | G32: R017 | H32: 0.49375 | I32: 0.49375 | J32: 0.49652778 | K32: 0.49652778 | L32: 0.49791667 | M32: =IF(N32="Delivered",IFERROR((L32-H32)*1440,""),"") -> 6 | N32: Delivered | P32: 370 | Q32: =IF(AND(I32<>"",J32<>""),(J32-I32)*1440,"") -> 4 | R32: =IF(H32<>"",HOUR(H32),"") -> 11 | S32: =IF(AND(N32="Delivered",M32<>"",M32>10),"Y","N") -> N
A33: 46280 | B33: ORD1030 | C33: Sanya Bhatia | D33: 9176936763 | E33: Sarjapur | F33: Swish Kitchen - Sarjapur | G33: R020 | H33: 0.44513889 | I33: 0.44513889 | J33: 0.45138889 | K33: 0.45138889 | L33: 0.45486111 | M33: =IF(N33="Delivered",IFERROR((L33-H33)*1440,""),"") -> 14 | N33: Delivered | O33: Rider took wrong route | P33: 344 | Q33: =IF(AND(I33<>"",J33<>""),(J33-I33)*1440,"") -> 9 | R33: =IF(H33<>"",HOUR(H33),"") -> 10 | S33: =IF(AND(N33="Delivered",M33<>"",M33>10),"Y","N") -> Y
A34: 46281 | B34: ORD1031 | C34: Aryan Bhatt | D34: 9708317278 | E34: HSR Layout | F34: Swish Kitchen - HSR Layout | G34: R003 | H34: 0.69305556 | I34: 0.69375 | J34: 0.7 | K34: 0.70069444 | L34: 0.70486111 | M34: =IF(N34="Delivered",IFERROR((L34-H34)*1440,""),"") -> 17 | N34: Delivered | O34: Address not found | P34: 636 | Q34: =IF(AND(I34<>"",J34<>""),(J34-I34)*1440,"") -> 9 | R34: =IF(H34<>"",HOUR(H34),"") -> 16 | S34: =IF(AND(N34="Delivered",M34<>"",M34>10),"Y","N") -> Y
A35: 46281 | B35: ORD1032 | C35: Dhruv Saxena | D35: 9277434873 | E35: Indiranagar | F35: Swish Kitchen - Indiranagar | G35: R006 | H35: 0.51944444 | I35: 0.51944444 | J35: 0.525 | K35: 0.52569444 | L35: 0.52777778 | M35: =IF(N35="Delivered",IFERROR((L35-H35)*1440,""),"") -> 12 | N35: Delivered | O35: Address not found | P35: 398 | Q35: =IF(AND(I35<>"",J35<>""),(J35-I35)*1440,"") -> 8 | R35: =IF(H35<>"",HOUR(H35),"") -> 12 | S35: =IF(AND(N35="Delivered",M35<>"",M35>10),"Y","N") -> Y
A36: 46281 | B36: ORD1033 | C36: Diya Mehta | D36: 9223623166 | E36: Whitefield | F36: Swish Kitchen - Whitefield | G36: R007 | H36: 0.56527778 | I36: 0.56597222 | J36: 0.57013889 | K36: 0.57013889 | L36: 0.57222222 | M36: =IF(N36="Delivered",IFERROR((L36-H36)*1440,""),"") -> 10 | N36: Delivered | P36: 550 | Q36: =IF(AND(I36<>"",J36<>""),(J36-I36)*1440,"") -> 6 | R36: =IF(H36<>"",HOUR(H36),"") -> 13 | S36: =IF(AND(N36="Delivered",M36<>"",M36>10),"Y","N") -> N
A37: 46281 | B37: ORD1034 | C37: Aarush Bali | D37: 9909670546 | E37: Electronic City | F37: Swish Kitchen - Electronic City | G37: R010 | H37: 0.91458333 | I37: 0.91527778 | J37: 0.92013889 | K37: 0.92152778 | L37: 0.92638889 | M37: =IF(N37="Delivered",IFERROR((L37-H37)*1440,""),"") -> 17 | N37: Delivered | O37: Heavy traffic | P37: 345 | Q37: =IF(AND(I37<>"",J37<>""),(J37-I37)*1440,"") -> 7 | R37: =IF(H37<>"",HOUR(H37),"") -> 21 | S37: =IF(AND(N37="Delivered",M37<>"",M37>10),"Y","N") -> Y
A38: 46281 | B38: ORD1035 | C38: Navya Desai | D38: 9706562729 | E38: Marathahalli | F38: Swish Kitchen - Marathahalli | G38: R011 | H38: 0.66736111 | M38: =IF(N38="Delivered",IFERROR((L38-H38)*1440,""),"") | N38: Cancelled | P38: 147 | Q38: =IF(AND(I38<>"",J38<>""),(J38-I38)*1440,"") | R38: =IF(H38<>"",HOUR(H38),"") -> 16 | S38: =IF(AND(N38="Delivered",M38<>"",M38>10),"Y","N") -> N
A39: 46281 | B39: ORD1036 | C39: Kiara Vora | D39: 9720465375 | E39: JP Nagar | F39: Swish Kitchen - JP Nagar | G39: R014 | H39: 0.575 | I39: 0.57569444 | J39: 0.57916667 | K39: 0.57986111 | L39: 0.58263889 | M39: =IF(N39="Delivered",IFERROR((L39-H39)*1440,""),"") -> 11 | N39: Delivered | O39: Rider took wrong route | P39: 203 | Q39: =IF(AND(I39<>"",J39<>""),(J39-I39)*1440,"") -> 5 | R39: =IF(H39<>"",HOUR(H39),"") -> 13 | S39: =IF(AND(N39="Delivered",M39<>"",M39>10),"Y","N") -> Y
A40: 46281 | B40: ORD1037 | C40: Tara Iyer | D40: 9053100330 | E40: BTM Layout | F40: Swish Kitchen - BTM Layout | G40: R015 | H40: 0.71458333 | I40: 0.71458333 | J40: 0.71736111 | K40: 0.71805556 | L40: 0.72291667 | M40: =IF(N40="Delivered",IFERROR((L40-H40)*1440,""),"") -> 12 | N40: Delivered | O40: Kitchen backlog | P40: 237 | Q40: =IF(AND(I40<>"",J40<>""),(J40-I40)*1440,"") -> 4 | R40: =IF(H40<>"",HOUR(H40),"") -> 17 | S40: =IF(AND(N40="Delivered",M40<>"",M40>10),"Y","N") -> Y
A41: 46281 | B41: ORD1038 | C41: Dhruv Saxena | D41: 9452991241 | E41: Bellandur | F41: Swish Kitchen - Bellandur | G41: R018 | H41: 0.70902778 | I41: 0.70972222 | J41: 0.71458333 | K41: 0.71597222 | L41: 0.71944444 | M41: =IF(N41="Delivered",IFERROR((L41-H41)*1440,""),"") -> 15 | N41: Delivered | O41: Kitchen backlog | P41: 526 | Q41: =IF(AND(I41<>"",J41<>""),(J41-I41)*1440,"") -> 7 | R41: =IF(H41<>"",HOUR(H41),"") -> 17 | S41: =IF(AND(N41="Delivered",M41<>"",M41>10),"Y","N") -> Y
A42: 46281 | B42: ORD1039 | C42: Diya Mehta | D42: 9931491905 | E42: Sarjapur | F42: Swish Kitchen - Sarjapur | G42: R019 | H42: 0.68541667 | M42: =IF(N42="Delivered",IFERROR((L42-H42)*1440,""),"") | N42: Cancelled | P42: 469 | Q42: =IF(AND(I42<>"",J42<>""),(J42-I42)*1440,"") | R42: =IF(H42<>"",HOUR(H42),"") -> 16 | S42: =IF(AND(N42="Delivered",M42<>"",M42>10),"Y","N") -> N
A43: 46281 | B43: ORD1040 | C43: Riya Kulkarni | D43: 9165726284 | E43: Koramangala | F43: Swish Kitchen - Koramangala | G43: R002 | H43: 0.74375 | I43: 0.74444444 | J43: 0.74861111 | K43: 0.74930556 | L43: 0.75416667 | M43: =IF(N43="Delivered",IFERROR((L43-H43)*1440,""),"") -> 15 | N43: Delivered | O43: Kitchen backlog | P43: 394 | Q43: =IF(AND(I43<>"",J43<>""),(J43-I43)*1440,"") -> 6 | R43: =IF(H43<>"",HOUR(H43),"") -> 17 | S43: =IF(AND(N43="Delivered",M43<>"",M43>10),"Y","N") -> Y
A44: 46281 | B44: ORD1041 | C44: Om Rathore | D44: 9147379965 | E44: HSR Layout | F44: Swish Kitchen - HSR Layout | G44: R003 | H44: 0.35486111 | I44: 0.35555556 | J44: 0.35833333 | K44: 0.35902778 | L44: 0.36111111 | M44: =IF(N44="Delivered",IFERROR((L44-H44)*1440,""),"") -> 9 | N44: Delivered | P44: 483 | Q44: =IF(AND(I44<>"",J44<>""),(J44-I44)*1440,"") -> 4 | R44: =IF(H44<>"",HOUR(H44),"") -> 8 | S44: =IF(AND(N44="Delivered",M44<>"",M44>10),"Y","N") -> N
A45: 46281 | B45: ORD1042 | C45: Arnav Sinha | D45: 9494808313 | E45: Indiranagar | F45: Swish Kitchen - Indiranagar | G45: R006 | H45: 0.80972222 | I45: 0.81041667 | J45: 0.81527778 | K45: 0.81527778 | L45: 0.82013889 | M45: =IF(N45="Delivered",IFERROR((L45-H45)*1440,""),"") -> 15 | N45: Delivered | O45: High order volume | P45: 607 | Q45: =IF(AND(I45<>"",J45<>""),(J45-I45)*1440,"") -> 7 | R45: =IF(H45<>"",HOUR(H45),"") -> 19 | S45: =IF(AND(N45="Delivered",M45<>"",M45>10),"Y","N") -> Y
A46: 46281 | B46: ORD1043 | C46: Dhruv Saxena | D46: 9014363495 | E46: Whitefield | F46: Swish Kitchen - Whitefield | G46: R007 | H46: 0.64930556 | I46: 0.65 | J46: 0.65416667 | K46: 0.65555556 | L46: 0.65972222 | M46: =IF(N46="Delivered",IFERROR((L46-H46)*1440,""),"") -> 15 | N46: Delivered | O46: High order volume | P46: 458 | Q46: =IF(AND(I46<>"",J46<>""),(J46-I46)*1440,"") -> 6 | R46: =IF(H46<>"",HOUR(H46),"") -> 15 | S46: =IF(AND(N46="Delivered",M46<>"",M46>10),"Y","N") -> Y
A47: 46281 | B47: ORD1044 | C47: Vivaan Chatterjee | D47: 9443135182 | E47: Electronic City | F47: Swish Kitchen - Electronic City | G47: R010 | H47: 0.46736111 | I47: 0.46805556 | J47: 0.47152778 | K47: 0.47291667 | L47: 0.47708333 | M47: =IF(N47="Delivered",IFERROR((L47-H47)*1440,""),"") -> 14 | N47: Delivered | O47: Peak hour surge | P47: 409 | Q47: =IF(AND(I47<>"",J47<>""),(J47-I47)*1440,"") -> 5 | R47: =IF(H47<>"",HOUR(H47),"") -> 11 | S47: =IF(AND(N47="Delivered",M47<>"",M47>10),"Y","N") -> Y
A48: 46281 | B48: ORD1045 | C48: Reyansh Jain | D48: 9435240824 | E48: Marathahalli | F48: Swish Kitchen - Marathahalli | G48: R011 | H48: 0.33541667 | I48: 0.33611111 | J48: 0.34166667 | K48: 0.34166667 | L48: 0.34652778 | M48: =IF(N48="Delivered",IFERROR((L48-H48)*1440,""),"") -> 16 | N48: Delivered | O48: Rider unavailable at pickup | P48: 622 | Q48: =IF(AND(I48<>"",J48<>""),(J48-I48)*1440,"") -> 8 | R48: =IF(H48<>"",HOUR(H48),"") -> 8 | S48: =IF(AND(N48="Delivered",M48<>"",M48>10),"Y","N") -> Y
A49: 46281 | B49: ORD1046 | C49: Advait Nambiar | D49: 9477752047 | E49: JP Nagar | F49: Swish Kitchen - JP Nagar | G49: R014 | H49: 0.41111111 | I49: 0.41111111 | J49: 0.41527778 | K49: 0.41597222 | L49: 0.41736111 | M49: =IF(N49="Delivered",IFERROR((L49-H49)*1440,""),"") -> 9 | N49: Delivered | P49: 174 | Q49: =IF(AND(I49<>"",J49<>""),(J49-I49)*1440,"") -> 6 | R49: =IF(H49<>"",HOUR(H49),"") -> 9 | S49: =IF(AND(N49="Delivered",M49<>"",M49>10),"Y","N") -> N
A50: 46281 | B50: ORD1047 | C50: Nitya Ghosh | D50: 9941318699 | E50: BTM Layout | F50: Swish Kitchen - BTM Layout | G50: R015 | H50: 0.86041667 | I50: 0.86041667 | J50: 0.86666667 | K50: 0.86805556 | L50: 0.87152778 | M50: =IF(N50="Delivered",IFERROR((L50-H50)*1440,""),"") -> 16 | N50: Delivered | O50: Heavy traffic | P50: 581 | Q50: =IF(AND(I50<>"",J50<>""),(J50-I50)*1440,"") -> 9 | R50: =IF(H50<>"",HOUR(H50),"") -> 20 | S50: =IF(AND(N50="Delivered",M50<>"",M50>10),"Y","N") -> Y
A51: 46281 | B51: ORD1048 | C51: Kiara Vora | D51: 9964990913 | E51: Bellandur | F51: Swish Kitchen - Bellandur | G51: R018 | H51: 0.75902778 | I51: 0.75972222 | J51: 0.76527778 | K51: 0.76527778 | L51: 0.76736111 | M51: =IF(N51="Delivered",IFERROR((L51-H51)*1440,""),"") -> 12 | N51: Delivered | O51: Rider unavailable at pickup | P51: 365 | Q51: =IF(AND(I51<>"",J51<>""),(J51-I51)*1440,"") -> 8 | R51: =IF(H51<>"",HOUR(H51),"") -> 18 | S51: =IF(AND(N51="Delivered",M51<>"",M51>10),"Y","N") -> Y
A52: 46281 | B52: ORD1049 | C52: Anika Bansal | D52: 9067974034 | E52: Sarjapur | F52: Swish Kitchen - Sarjapur | G52: R019 | H52: 0.80416667 | I52: 0.80486111 | J52: 0.80694444 | K52: 0.80833333 | L52: 0.81041667 | M52: =IF(N52="Delivered",IFERROR((L52-H52)*1440,""),"") -> 9 | N52: Delivered | P52: 390 | Q52: =IF(AND(I52<>"",J52<>""),(J52-I52)*1440,"") -> 3 | R52: =IF(H52<>"",HOUR(H52),"") -> 19 | S52: =IF(AND(N52="Delivered",M52<>"",M52>10),"Y","N") -> N
A53: 46281 | B53: ORD1050 | C53: Ved Trivedi | D53: 9936183242 | E53: Koramangala | F53: Swish Kitchen - Koramangala | G53: R002 | H53: 0.37708333 | I53: 0.37708333 | J53: 0.38333333 | K53: 0.38402778 | L53: 0.38819444 | M53: =IF(N53="Delivered",IFERROR((L53-H53)*1440,""),"") -> 16 | N53: Delivered | O53: High order volume | P53: 415 | Q53: =IF(AND(I53<>"",J53<>""),(J53-I53)*1440,"") -> 9 | R53: =IF(H53<>"",HOUR(H53),"") -> 9 | S53: =IF(AND(N53="Delivered",M53<>"",M53>10),"Y","N") -> Y
A54: 46281 | B54: ORD1051 | C54: Krish Choudhary | D54: 9464887719 | E54: HSR Layout | F54: Swish Kitchen - HSR Layout | G54: R003 | H54: 0.37222222 | I54: 0.37291667 | M54: =IF(N54="Delivered",IFERROR((L54-H54)*1440,""),"") | N54: Cancelled | P54: 376 | Q54: =IF(AND(I54<>"",J54<>""),(J54-I54)*1440,"") | R54: =IF(H54<>"",HOUR(H54),"") -> 8 | S54: =IF(AND(N54="Delivered",M54<>"",M54>10),"Y","N") -> N
A55: 46281 | B55: ORD1052 | C55: Anaya Pillai | D55: 9990490278 | E55: Indiranagar | F55: Swish Kitchen - Indiranagar | G55: R006 | H55: 0.76944444 | I55: 0.77013889 | J55: 0.77291667 | K55: 0.77430556 | L55: 0.77777778 | M55: =IF(N55="Delivered",IFERROR((L55-H55)*1440,""),"") -> 12 | N55: Delivered | O55: High order volume | P55: 623 | Q55: =IF(AND(I55<>"",J55<>""),(J55-I55)*1440,"") -> 4 | R55: =IF(H55<>"",HOUR(H55),"") -> 18 | S55: =IF(AND(N55="Delivered",M55<>"",M55>10),"Y","N") -> Y
A56: 46281 | B56: ORD1053 | C56: Zara Ahmed | D56: 9655125674 | E56: Whitefield | F56: Swish Kitchen - Whitefield | G56: R007 | H56: 0.76736111 | I56: 0.76736111 | J56: 0.77152778 | K56: 0.77152778 | L56: 0.77430556 | M56: =IF(N56="Delivered",IFERROR((L56-H56)*1440,""),"") -> 10 | N56: Delivered | P56: 378 | Q56: =IF(AND(I56<>"",J56<>""),(J56-I56)*1440,"") -> 6 | R56: =IF(H56<>"",HOUR(H56),"") -> 18 | S56: =IF(AND(N56="Delivered",M56<>"",M56>10),"Y","N") -> Y
A57: 46281 | B57: ORD1054 | C57: Aarush Bali | D57: 9680876038 | E57: Electronic City | F57: Swish Kitchen - Electronic City | G57: R010 | H57: 0.56875 | I57: 0.56944444 | J57: 0.575 | K57: 0.57569444 | L57: 0.57708333 | M57: =IF(N57="Delivered",IFERROR((L57-H57)*1440,""),"") -> 12 | N57: Delivered | O57: Kitchen backlog | P57: 328 | Q57: =IF(AND(I57<>"",J57<>""),(J57-I57)*1440,"") -> 8 | R57: =IF(H57<>"",HOUR(H57),"") -> 13 | S57: =IF(AND(N57="Delivered",M57<>"",M57>10),"Y","N") -> Y
A58: 46281 | B58: ORD1055 | C58: Pihu Agarwal | D58: 9477109324 | E58: Marathahalli | F58: Swish Kitchen - Marathahalli | G58: R011 | H58: 0.66666667 | I58: 0.66736111 | J58: 0.66944444 | K58: 0.66944444 | L58: 0.67083333 | M58: =IF(N58="Delivered",IFERROR((L58-H58)*1440,""),"") -> 6 | N58: Delivered | P58: 592 | Q58: =IF(AND(I58<>"",J58<>""),(J58-I58)*1440,"") -> 3 | R58: =IF(H58<>"",HOUR(H58),"") -> 16 | S58: =IF(AND(N58="Delivered",M58<>"",M58>10),"Y","N") -> N
A59: 46281 | B59: ORD1056 | C59: Ved Trivedi | D59: 9274846773 | E59: JP Nagar | F59: Swish Kitchen - JP Nagar | G59: R014 | H59: 0.64930556 | I59: 0.64930556 | J59: 0.65347222 | K59: 0.65347222 | L59: 0.65763889 | M59: =IF(N59="Delivered",IFERROR((L59-H59)*1440,""),"") -> 12 | N59: Delivered | O59: Kitchen backlog | P59: 640 | Q59: =IF(AND(I59<>"",J59<>""),(J59-I59)*1440,"") -> 6 | R59: =IF(H59<>"",HOUR(H59),"") -> 15 | S59: =IF(AND(N59="Delivered",M59<>"",M59>10),"Y","N") -> Y
A60: 46281 | B60: ORD1057 | C60: Kiara Vora | D60: 9146584044 | E60: BTM Layout | F60: Swish Kitchen - BTM Layout | G60: R015 | H60: 0.90069444 | I60: 0.90138889 | J60: 0.90763889 | K60: 0.90763889 | L60: 0.91111111 | M60: =IF(N60="Delivered",IFERROR((L60-H60)*1440,""),"") -> 15 | N60: Delivered | O60: Address not found | P60: 615 | Q60: =IF(AND(I60<>"",J60<>""),(J60-I60)*1440,"") -> 9 | R60: =IF(H60<>"",HOUR(H60),"") -> 21 | S60: =IF(AND(N60="Delivered",M60<>"",M60>10),"Y","N") -> Y
A61: 46281 | B61: ORD1058 | C61: Aarush Bali | D61: 9867533963 | E61: Bellandur | F61: Swish Kitchen - Bellandur | G61: R018 | H61: 0.90902778 | I61: 0.90972222 | J61: 0.91180556 | K61: 0.9125 | L61: 0.91736111 | M61: =IF(N61="Delivered",IFERROR((L61-H61)*1440,""),"") -> 12 | N61: Delivered | O61: Peak hour surge | P61: 604 | Q61: =IF(AND(I61<>"",J61<>""),(J61-I61)*1440,"") -> 3 | R61: =IF(H61<>"",HOUR(H61),"") -> 21 | S61: =IF(AND(N61="Delivered",M61<>"",M61>10),"Y","N") -> Y
A62: 46281 | B62: ORD1059 | C62: Kian Fernandes | D62: 9627028951 | E62: Sarjapur | F62: Swish Kitchen - Sarjapur | G62: R019 | H62: 0.9125 | I62: 0.91319444 | J62: 0.91527778 | K62: 0.91666667 | L62: 0.92013889 | M62: =IF(N62="Delivered",IFERROR((L62-H62)*1440,""),"") -> 11 | N62: Delivered | O62: High order volume | P62: 135 | Q62: =IF(AND(I62<>"",J62<>""),(J62-I62)*1440,"") -> 3 | R62: =IF(H62<>"",HOUR(H62),"") -> 21 | S62: =IF(AND(N62="Delivered",M62<>"",M62>10),"Y","N") -> Y
A63: 46281 | B63: ORD1060 | C63: Kiara Vora | D63: 9217459615 | E63: Koramangala | F63: Swish Kitchen - Koramangala | G63: R002 | H63: 0.90486111 | I63: 0.90555556 | J63: 0.90902778 | K63: 0.91041667 | L63: 0.91527778 | M63: =IF(N63="Delivered",IFERROR((L63-H63)*1440,""),"") -> 15 | N63: Delivered | O63: Rider unavailable at pickup | P63: 619 | Q63: =IF(AND(I63<>"",J63<>""),(J63-I63)*1440,"") -> 5 | R63: =IF(H63<>"",HOUR(H63),"") -> 21 | S63: =IF(AND(N63="Delivered",M63<>"",M63>10),"Y","N") -> Y
A64: 46282 | B64: ORD1061 | C64: Sanya Bhatia | D64: 9134316117 | E64: Indiranagar | F64: Swish Kitchen - Indiranagar | G64: R005 | H64: 0.44722222 | I64: 0.44791667 | J64: 0.45 | K64: 0.45 | L64: 0.45277778 | M64: =IF(N64="Delivered",IFERROR((L64-H64)*1440,""),"") -> 8 | N64: Delivered | P64: 177 | Q64: =IF(AND(I64<>"",J64<>""),(J64-I64)*1440,"") -> 3 | R64: =IF(H64<>"",HOUR(H64),"") -> 10 | S64: =IF(AND(N64="Delivered",M64<>"",M64>10),"Y","N") -> N
A65: 46282 | B65: ORD1062 | C65: Zara Ahmed | D65: 9623869222 | E65: Whitefield | F65: Swish Kitchen - Whitefield | G65: R008 | H65: 0.40208333 | I65: 0.40277778 | J65: 0.40763889 | K65: 0.40902778 | L65: 0.41111111 | M65: =IF(N65="Delivered",IFERROR((L65-H65)*1440,""),"") -> 13 | N65: Delivered | O65: Kitchen backlog | P65: 629 | Q65: =IF(AND(I65<>"",J65<>""),(J65-I65)*1440,"") -> 7 | R65: =IF(H65<>"",HOUR(H65),"") -> 9 | S65: =IF(AND(N65="Delivered",M65<>"",M65>10),"Y","N") -> Y
A66: 46282 | B66: ORD1063 | C66: Myra Kapoor | D66: 9747407482 | E66: Electronic City | F66: Swish Kitchen - Electronic City | G66: R009 | H66: 0.39444444 | I66: 0.39513889 | J66: 0.4 | K66: 0.40069444 | L66: 0.40555556 | M66: =IF(N66="Delivered",IFERROR((L66-H66)*1440,""),"") -> 16 | N66: Delivered | O66: High order volume | P66: 554 | Q66: =IF(AND(I66<>"",J66<>""),(J66-I66)*1440,"") -> 7 | R66: =IF(H66<>"",HOUR(H66),"") -> 9 | S66: =IF(AND(N66="Delivered",M66<>"",M66>10),"Y","N") -> Y
A67: 46282 | B67: ORD1064 | C67: Kiara Vora | D67: 9436713695 | E67: Marathahalli | F67: Swish Kitchen - Marathahalli | G67: R012 | H67: 0.72083333 | M67: =IF(N67="Delivered",IFERROR((L67-H67)*1440,""),"") | N67: Cancelled | P67: 401 | Q67: =IF(AND(I67<>"",J67<>""),(J67-I67)*1440,"") | R67: =IF(H67<>"",HOUR(H67),"") -> 17 | S67: =IF(AND(N67="Delivered",M67<>"",M67>10),"Y","N") -> N
A68: 46282 | B68: ORD1065 | C68: Aarush Bali | D68: 9097439533 | E68: JP Nagar | F68: Swish Kitchen - JP Nagar | G68: R013 | H68: 0.71944444 | I68: 0.71944444 | J68: 0.725 | K68: 0.725 | L68: 0.72986111 | M68: =IF(N68="Delivered",IFERROR((L68-H68)*1440,""),"") -> 15 | N68: Delivered | O68: High order volume | P68: 160 | Q68: =IF(AND(I68<>"",J68<>""),(J68-I68)*1440,"") -> 8 | R68: =IF(H68<>"",HOUR(H68),"") -> 17 | S68: =IF(AND(N68="Delivered",M68<>"",M68>10),"Y","N") -> Y
A69: 46282 | B69: ORD1066 | C69: Ishaan Gupta | D69: 9952145623 | E69: BTM Layout | F69: Swish Kitchen - BTM Layout | G69: R016 | H69: 0.45138889 | I69: 0.45208333 | J69: 0.45694444 | K69: 0.45833333 | L69: 0.46111111 | M69: =IF(N69="Delivered",IFERROR((L69-H69)*1440,""),"") -> 14 | N69: Delivered | O69: Peak hour surge | P69: 288 | Q69: =IF(AND(I69<>"",J69<>""),(J69-I69)*1440,"") -> 7 | R69: =IF(H69<>"",HOUR(H69),"") -> 10 | S69: =IF(AND(N69="Delivered",M69<>"",M69>10),"Y","N") -> Y
A70: 46282 | B70: ORD1067 | C70: Riya Kulkarni | D70: 9451712368 | E70: Bellandur | F70: Swish Kitchen - Bellandur | G70: R017 | H70: 0.54513889 | I70: 0.54583333 | J70: 0.54791667 | K70: 0.54861111 | L70: 0.55277778 | M70: =IF(N70="Delivered",IFERROR((L70-H70)*1440,""),"") -> 11 | N70: Delivered | O70: Rider took wrong route | P70: 246 | Q70: =IF(AND(I70<>"",J70<>""),(J70-I70)*1440,"") -> 3 | R70: =IF(H70<>"",HOUR(H70),"") -> 13 | S70: =IF(AND(N70="Delivered",M70<>"",M70>10),"Y","N") -> Y
A71: 46282 | B71: ORD1068 | C71: Ira Sharma | D71: 9496513709 | E71: Sarjapur | F71: Swish Kitchen - Sarjapur | G71: R020 | H71: 0.68055556 | I71: 0.68055556 | J71: 0.68611111 | K71: 0.68611111 | L71: 0.69097222 | M71: =IF(N71="Delivered",IFERROR((L71-H71)*1440,""),"") -> 15 | N71: Delivered | O71: Heavy traffic | P71: 595 | Q71: =IF(AND(I71<>"",J71<>""),(J71-I71)*1440,"") -> 8 | R71: =IF(H71<>"",HOUR(H71),"") -> 16 | S71: =IF(AND(N71="Delivered",M71<>"",M71>10),"Y","N") -> Y
A72: 46282 | B72: ORD1069 | C72: Ved Trivedi | D72: 9612004711 | E72: Koramangala | F72: Swish Kitchen - Koramangala | G72: R001 | H72: 0.49722222 | I72: 0.49722222 | J72: 0.50138889 | K72: 0.50208333 | L72: 0.50486111 | M72: =IF(N72="Delivered",IFERROR((L72-H72)*1440,""),"") -> 11 | N72: Delivered | O72: Rider took wrong route | P72: 549 | Q72: =IF(AND(I72<>"",J72<>""),(J72-I72)*1440,"") -> 6 | R72: =IF(H72<>"",HOUR(H72),"") -> 11 | S72: =IF(AND(N72="Delivered",M72<>"",M72>10),"Y","N") -> Y
A73: 46282 | B73: ORD1070 | C73: Kabir Malhotra | D73: 9617964053 | E73: HSR Layout | F73: Swish Kitchen - HSR Layout | G73: R004 | H73: 0.64444444 | I73: 0.64444444 | J73: 0.65069444 | K73: 0.65138889 | L73: 0.65277778 | M73: =IF(N73="Delivered",IFERROR((L73-H73)*1440,""),"") -> 12 | N73: Delivered | O73: Rider took wrong route | P73: 496 | Q73: =IF(AND(I73<>"",J73<>""),(J73-I73)*1440,"") -> 9 | R73: =IF(H73<>"",HOUR(H73),"") -> 15 | S73: =IF(AND(N73="Delivered",M73<>"",M73>10),"Y","N") -> Y
A74: 46282 | B74: ORD1071 | C74: Zara Ahmed | D74: 9064317139 | E74: Indiranagar | F74: Swish Kitchen - Indiranagar | G74: R005 | H74: 0.33541667 | M74: =IF(N74="Delivered",IFERROR((L74-H74)*1440,""),"") | N74: Cancelled | P74: 330 | Q74: =IF(AND(I74<>"",J74<>""),(J74-I74)*1440,"") | R74: =IF(H74<>"",HOUR(H74),"") -> 8 | S74: =IF(AND(N74="Delivered",M74<>"",M74>10),"Y","N") -> N
A75: 46282 | B75: ORD1072 | C75: Reyansh Jain | D75: 9933529042 | E75: Whitefield | F75: Swish Kitchen - Whitefield | G75: R008 | H75: 0.44027778 | I75: 0.44097222 | J75: 0.44722222 | K75: 0.44722222 | L75: 0.44861111 | M75: =IF(N75="Delivered",IFERROR((L75-H75)*1440,""),"") -> 12 | N75: Delivered | O75: Heavy traffic | P75: 146 | Q75: =IF(AND(I75<>"",J75<>""),(J75-I75)*1440,"") -> 9 | R75: =IF(H75<>"",HOUR(H75),"") -> 10 | S75: =IF(AND(N75="Delivered",M75<>"",M75>10),"Y","N") -> Y
A76: 46282 | B76: ORD1073 | C76: Nitya Ghosh | D76: 9395024026 | E76: Electronic City | F76: Swish Kitchen - Electronic City | G76: R009 | H76: 0.67152778 | I76: 0.67152778 | J76: 0.67569444 | K76: 0.67638889 | L76: 0.67916667 | M76: =IF(N76="Delivered",IFERROR((L76-H76)*1440,""),"") -> 11 | N76: Delivered | O76: High order volume | P76: 645 | Q76: =IF(AND(I76<>"",J76<>""),(J76-I76)*1440,"") -> 6 | R76: =IF(H76<>"",HOUR(H76),"") -> 16 | S76: =IF(AND(N76="Delivered",M76<>"",M76>10),"Y","N") -> Y
A77: 46282 | B77: ORD1074 | C77: Aryan Bhatt | D77: 9390847007 | E77: Marathahalli | F77: Swish Kitchen - Marathahalli | G77: R012 | H77: 0.89236111 | I77: 0.89305556 | M77: =IF(N77="Delivered",IFERROR((L77-H77)*1440,""),"") | N77: Cancelled | P77: 574 | Q77: =IF(AND(I77<>"",J77<>""),(J77-I77)*1440,"") | R77: =IF(H77<>"",HOUR(H77),"") -> 21 | S77: =IF(AND(N77="Delivered",M77<>"",M77>10),"Y","N") -> N
A78: 46282 | B78: ORD1075 | C78: Sanya Bhatia | D78: 9212499856 | E78: JP Nagar | F78: Swish Kitchen - JP Nagar | G78: R013 | H78: 0.73125 | M78: =IF(N78="Delivered",IFERROR((L78-H78)*1440,""),"") | N78: Cancelled | P78: 560 | Q78: =IF(AND(I78<>"",J78<>""),(J78-I78)*1440,"") | R78: =IF(H78<>"",HOUR(H78),"") -> 17 | S78: =IF(AND(N78="Delivered",M78<>"",M78>10),"Y","N") -> N
A79: 46282 | B79: ORD1076 | C79: Kiara Vora | D79: 9836736576 | E79: BTM Layout | F79: Swish Kitchen - BTM Layout | G79: R016 | H79: 0.61527778 | I79: 0.61527778 | J79: 0.61875 | K79: 0.61944444 | L79: 0.62222222 | M79: =IF(N79="Delivered",IFERROR((L79-H79)*1440,""),"") -> 10 | N79: Delivered | P79: 381 | Q79: =IF(AND(I79<>"",J79<>""),(J79-I79)*1440,"") -> 5 | R79: =IF(H79<>"",HOUR(H79),"") -> 14 | S79: =IF(AND(N79="Delivered",M79<>"",M79>10),"Y","N") -> N
A80: 46282 | B80: ORD1077 | C80: Kabir Malhotra | D80: 9711116152 | E80: Bellandur | F80: Swish Kitchen - Bellandur | G80: R017 | H80: 0.66875 | I80: 0.66944444 | J80: 0.675 | K80: 0.675 | L80: 0.67847222 | M80: =IF(N80="Delivered",IFERROR((L80-H80)*1440,""),"") -> 14 | N80: Delivered | O80: Peak hour surge | P80: 482 | Q80: =IF(AND(I80<>"",J80<>""),(J80-I80)*1440,"") -> 8 | R80: =IF(H80<>"",HOUR(H80),"") -> 16 | S80: =IF(AND(N80="Delivered",M80<>"",M80>10),"Y","N") -> Y
A81: 46282 | B81: ORD1078 | C81: Navya Desai | D81: 9049451983 | E81: Sarjapur | F81: Swish Kitchen - Sarjapur | G81: R020 | H81: 0.44583333 | I81: 0.44652778 | J81: 0.44930556 | K81: 0.44930556 | L81: 0.45208333 | M81: =IF(N81="Delivered",IFERROR((L81-H81)*1440,""),"") -> 9 | N81: Delivered | P81: 496 | Q81: =IF(AND(I81<>"",J81<>""),(J81-I81)*1440,"") -> 4 | R81: =IF(H81<>"",HOUR(H81),"") -> 10 | S81: =IF(AND(N81="Delivered",M81<>"",M81>10),"Y","N") -> N
A82: 46282 | B82: ORD1079 | C82: Vivaan Chatterjee | D82: 9936899809 | E82: Koramangala | F82: Swish Kitchen - Koramangala | G82: R001 | H82: 0.78680556 | I82: 0.7875 | J82: 0.78958333 | K82: 0.78958333 | L82: 0.79236111 | M82: =IF(N82="Delivered",IFERROR((L82-H82)*1440,""),"") -> 8 | N82: Delivered | P82: 436 | Q82: =IF(AND(I82<>"",J82<>""),(J82-I82)*1440,"") -> 3 | R82: =IF(H82<>"",HOUR(H82),"") -> 18 | S82: =IF(AND(N82="Delivered",M82<>"",M82>10),"Y","N") -> N
A83: 46282 | B83: ORD1080 | C83: Zara Ahmed | D83: 9022961201 | E83: HSR Layout | F83: Swish Kitchen - HSR Layout | G83: R004 | H83: 0.81458333 | I83: 0.81458333 | J83: 0.81875 | K83: 0.81944444 | L83: 0.82291667 | M83: =IF(N83="Delivered",IFERROR((L83-H83)*1440,""),"") -> 12 | N83: Delivered | O83: Heavy traffic | P83: 469 | Q83: =IF(AND(I83<>"",J83<>""),(J83-I83)*1440,"") -> 6 | R83: =IF(H83<>"",HOUR(H83),"") -> 19 | S83: =IF(AND(N83="Delivered",M83<>"",M83>10),"Y","N") -> Y
A84: 46282 | B84: ORD1081 | C84: Ira Sharma | D84: 9599102290 | E84: Indiranagar | F84: Swish Kitchen - Indiranagar | G84: R005 | H84: 0.75347222 | I84: 0.75416667 | J84: 0.75833333 | K84: 0.75972222 | L84: 0.76319444 | M84: =IF(N84="Delivered",IFERROR((L84-H84)*1440,""),"") -> 14 | N84: Delivered | O84: High order volume | P84: 617 | Q84: =IF(AND(I84<>"",J84<>""),(J84-I84)*1440,"") -> 6 | R84: =IF(H84<>"",HOUR(H84),"") -> 18 | S84: =IF(AND(N84="Delivered",M84<>"",M84>10),"Y","N") -> Y
A85: 46282 | B85: ORD1082 | C85: Vivaan Chatterjee | D85: 9381561497 | E85: Whitefield | F85: Swish Kitchen - Whitefield | G85: R008 | H85: 0.69583333 | I85: 0.69652778 | M85: =IF(N85="Delivered",IFERROR((L85-H85)*1440,""),"") | N85: Cancelled | P85: 176 | Q85: =IF(AND(I85<>"",J85<>""),(J85-I85)*1440,"") | R85: =IF(H85<>"",HOUR(H85),"") -> 16 | S85: =IF(AND(N85="Delivered",M85<>"",M85>10),"Y","N") -> N
A86: 46282 | B86: ORD1083 | C86: Reyansh Jain | D86: 9244510762 | E86: Electronic City | F86: Swish Kitchen - Electronic City | G86: R009 | H86: 0.43333333 | M86: =IF(N86="Delivered",IFERROR((L86-H86)*1440,""),"") | N86: Pending | P86: 482 | Q86: =IF(AND(I86<>"",J86<>""),(J86-I86)*1440,"") | R86: =IF(H86<>"",HOUR(H86),"") -> 10 | S86: =IF(AND(N86="Delivered",M86<>"",M86>10),"Y","N") -> N
A87: 46282 | B87: ORD1084 | C87: Kian Fernandes | D87: 9060715969 | E87: Marathahalli | F87: Swish Kitchen - Marathahalli | G87: R012 | H87: 0.61458333 | I87: 0.61527778 | J87: 0.61875 | M87: =IF(N87="Delivered",IFERROR((L87-H87)*1440,""),"") | N87: Ready | P87: 141 | Q87: =IF(AND(I87<>"",J87<>""),(J87-I87)*1440,"") -> 5 | R87: =IF(H87<>"",HOUR(H87),"") -> 14 | S87: =IF(AND(N87="Delivered",M87<>"",M87>10),"Y","N") -> N
A88: 46282 | B88: ORD1085 | C88: Anika Bansal | D88: 9975161369 | E88: JP Nagar | F88: Swish Kitchen - JP Nagar | G88: R013 | H88: 0.60625 | I88: 0.60625 | M88: =IF(N88="Delivered",IFERROR((L88-H88)*1440,""),"") | N88: Preparing | P88: 467 | Q88: =IF(AND(I88<>"",J88<>""),(J88-I88)*1440,"") | R88: =IF(H88<>"",HOUR(H88),"") -> 14 | S88: =IF(AND(N88="Delivered",M88<>"",M88>10),"Y","N") -> N
A89: 46282 | B89: ORD1086 | C89: Arnav Sinha | D89: 9218188355 | E89: BTM Layout | F89: Swish Kitchen - BTM Layout | G89: R016 | H89: 0.82777778 | I89: 0.82777778 | M89: =IF(N89="Delivered",IFERROR((L89-H89)*1440,""),"") | N89: Preparing | P89: 382 | Q89: =IF(AND(I89<>"",J89<>""),(J89-I89)*1440,"") | R89: =IF(H89<>"",HOUR(H89),"") -> 19 | S89: =IF(AND(N89="Delivered",M89<>"",M89>10),"Y","N") -> N
A90: 46282 | B90: ORD1087 | C90: Anika Bansal | D90: 9921277997 | E90: Bellandur | F90: Swish Kitchen - Bellandur | G90: R017 | H90: 0.79097222 | I90: 0.79166667 | J90: 0.79791667 | K90: 0.79930556 | M90: =IF(N90="Delivered",IFERROR((L90-H90)*1440,""),"") | N90: Picked Up | P90: 274 | Q90: =IF(AND(I90<>"",J90<>""),(J90-I90)*1440,"") -> 9 | R90: =IF(H90<>"",HOUR(H90),"") -> 18 | S90: =IF(AND(N90="Delivered",M90<>"",M90>10),"Y","N") -> N
A91: 46282 | B91: ORD1088 | C91: Diya Mehta | D91: 9774490581 | E91: Sarjapur | F91: Swish Kitchen - Sarjapur | G91: R020 | H91: 0.52013889 | M91: =IF(N91="Delivered",IFERROR((L91-H91)*1440,""),"") | N91: Pending | P91: 413 | Q91: =IF(AND(I91<>"",J91<>""),(J91-I91)*1440,"") | R91: =IF(H91<>"",HOUR(H91),"") -> 12 | S91: =IF(AND(N91="Delivered",M91<>"",M91>10),"Y","N") -> N
A92: 46282 | B92: ORD1089 | C92: Ved Trivedi | D92: 9199867980 | E92: Koramangala | F92: Swish Kitchen - Koramangala | G92: R001 | H92: 0.66527778 | I92: 0.66527778 | M92: =IF(N92="Delivered",IFERROR((L92-H92)*1440,""),"") | N92: Preparing | P92: 633 | Q92: =IF(AND(I92<>"",J92<>""),(J92-I92)*1440,"") | R92: =IF(H92<>"",HOUR(H92),"") -> 15 | S92: =IF(AND(N92="Delivered",M92<>"",M92>10),"Y","N") -> N
A93: 46282 | B93: ORD1090 | C93: Ishaan Gupta | D93: 9715182037 | E93: HSR Layout | F93: Swish Kitchen - HSR Layout | G93: R004 | H93: 0.64791667 | I93: 0.64791667 | J93: 0.65138889 | K93: 0.65208333 | M93: =IF(N93="Delivered",IFERROR((L93-H93)*1440,""),"") | N93: Picked Up | P93: 516 | Q93: =IF(AND(I93<>"",J93<>""),(J93-I93)*1440,"") -> 5 | R93: =IF(H93<>"",HOUR(H93),"") -> 15 | S93: =IF(AND(N93="Delivered",M93<>"",M93>10),"Y","N") -> N

Sheet Hourly_Helper
A1: Kitchen | B1: 0 | C1: 1 | D1: 2 | E1: 3 | F1: 4 | G1: 5 | H1: 6 | I1: 7 | J1: 8 | K1: 9 | L1: 10 | M1: 11 | N1: 12 | O1: 13 | P1: 14 | Q1: 15 | R1: 16 | S1: 17 | T1: 18 | U1: 19 | V1: 20 | W1: 21 | X1: 22 | Y1: 23 | Z1: Peak Hour Load | AA1: Late Night 0-3 | AB1: Early Morn 4-7 | AC1: Morning 8-11 | AD1: Afternoon 12-15 | AE1: Evening 16-19 | AF1: Night 20-23
A2: Swish Kitchen - Koramangala | B2: =COUNTIFS('Daily Order Tracker'!$F$4:$F$93,$A2,'Daily Order Tracker'!$R$4:$R$93,0) -> 0 | C2: =COUNTIFS('Daily Order Tracker'!$F$4:$F$93,$A2,'Daily Order Tracker'!$R$4:$R$93,1) -> 0 | D2: =COUNTIFS('Daily Order Tracker'!$F$4:$F$93,$A2,'Daily Order Tracker'!$R$4:$R$93,2) -> 0 | E2: =COUNTIFS('Daily Order Tracker'!$F$4:$F$93,$A2,'Daily Order Tracker'!$R$4:$R$93,3) -> 0 | F2: =COUNTIFS('Daily Order Tracker'!$F$4:$F$93,$A2,'Daily Order Tracker'!$R$4:$R$93,4) -> 0 | G2: =COUNTIFS('Daily Order Tracker'!$F$4:$F$93,$A2,'Daily Order Tracker'!$R$4:$R$93,5) -> 0 | H2: =COUNTIFS('Daily Order Tracker'!$F$4:$F$93,$A2,'Daily Order Tracker'!$R$4:$R$93,6) -> 0 | I2: =COUNTIFS('Daily Order Tracker'!$F$4:$F$93,$A2,'Daily Order Tracker'!$R$4:$R$93,7) -> 0 | J2: =COUNTIFS('Daily Order Tracker'!$F$4:$F$93,$A2,'Daily Order Tracker'!$R$4:$R$93,8) -> 0 | K2: =COUNTIFS('Daily Order Tracker'!$F$4:$F$93,$A2,'Daily Order Tracker'!$R$4:$R$93,9) -> 1 | L2: =COUNTIFS('Daily Order Tracker'!$F$4:$F$93,$A2,'Daily Order Tracker'!$R$4:$R$93,10) -> 0 | M2: =COUNTIFS('Daily Order Tracker'!$F$4:$F$93,$A2,'Daily Order Tracker'!$R$4:$R$93,11) -> 1 | N2: =COUNTIFS('Daily Order Tracker'!$F$4:$F$93,$A2,'Daily Order Tracker'!$R$4:$R$93,12) -> 0 | O2: =COUNTIFS('Daily Order Tracker'!$F$4:$F$93,$A2,'Daily Order Tracker'!$R$4:$R$93,13) -> 0 | P2: =COUNTIFS('Daily Order Tracker'!$F$4:$F$93,$A2,'Daily Order Tracker'!$R$4:$R$93,14) -> 0 | Q2: =COUNTIFS('Daily Order Tracker'!$F$4:$F$93,$A2,'Daily Order Tracker'!$R$4:$R$93,15) -> 2 | R2: =COUNTIFS('Daily Order Tracker'!$F$4:$F$93,$A2,'Daily Order Tracker'!$R$4:$R$93,16) -> 0 | S2: =COUNTIFS('Daily Order Tracker'!$F$4:$F$93,$A2,'Daily Order Tracker'!$R$4:$R$93,17) -> 2 | T2: =COUNTIFS('Daily Order Tracker'!$F$4:$F$93,$A2,'Daily Order Tracker'!$R$4:$R$93,18) -> 1 | U2: =COUNTIFS('Daily Order Tracker'!$F$4:$F$93,$A2,'Daily Order Tracker'!$R$4:$R$93,19) -> 0 | V2: =COUNTIFS('Daily Order Tracker'!$F$4:$F$93,$A2,'Daily Order Tracker'!$R$4:$R$93,20) -> 0 | W2: =COUNTIFS('Daily Order Tracker'!$F$4:$F$93,$A2,'Daily Order Tracker'!$R$4:$R$93,21) -> 2 | X2: =COUNTIFS('Daily Order Tracker'!$F$4:$F$93,$A2,'Daily Order Tracker'!$R$4:$R$93,22) -> 0 | Y2: =COUNTIFS('Daily Order Tracker'!$F$4:$F$93,$A2,'Daily Order Tracker'!$R$4:$R$93,23) -> 0 | Z2: =MAX(B2:Y2) -> 2 | AA2: =SUM(B2:E2) -> 0 | AB2: =SUM(F2:I2) -> 0 | AC2: =SUM(J2:M2) -> 2 | AD2: =SUM(N2:Q2) -> 2 | AE2: =SUM(R2:U2) -> 3 | AF2: =SUM(V2:Y2) -> 2
A3: Swish Kitchen - HSR Layout | B3: =COUNTIFS('Daily Order Tracker'!$F$4:$F$93,$A3,'Daily Order Tracker'!$R$4:$R$93,0) -> 0 | C3: =COUNTIFS('Daily Order Tracker'!$F$4:$F$93,$A3,'Daily Order Tracker'!$R$4:$R$93,1) -> 0 | D3: =COUNTIFS('Daily Order Tracker'!$F$4:$F$93,$A3,'Daily Order Tracker'!$R$4:$R$93,2) -> 0 | E3: =COUNTIFS('Daily Order Tracker'!$F$4:$F$93,$A3,'Daily Order Tracker'!$R$4:$R$93,3) -> 0 | F3: =COUNTIFS('Daily Order Tracker'!$F$4:$F$93,$A3,'Daily Order Tracker'!$R$4:$R$93,4) -> 0 | G3: =COUNTIFS('Daily Order Tracker'!$F$4:$F$93,$A3,'Daily Order Tracker'!$R$4:$R$93,5) -> 0 | H3: =COUNTIFS('Daily Order Tracker'!$F$4:$F$93,$A3,'Daily Order Tracker'!$R$4:$R$93,6) -> 0 | I3: =COUNTIFS('Daily Order Tracker'!$F$4:$F$93,$A3,'Daily Order Tracker'!$R$4:$R$93,7) -> 0 | J3: =COUNTIFS('Daily Order Tracker'!$F$4:$F$93,$A3,'Daily Order Tracker'!$R$4:$R$93,8) -> 2 | K3: =COUNTIFS('Daily Order Tracker'!$F$4:$F$93,$A3,'Daily Order Tracker'!$R$4:$R$93,9) -> 1 | L3: =COUNTIFS('Daily Order Tracker'!$F$4:$F$93,$A3,'Daily Order Tracker'!$R$4:$R$93,10) -> 0 | M3: =COUNTIFS('Daily Order Tracker'!$F$4:$F$93,$A3,'Daily Order Tracker'!$R$4:$R$93,11) -> 0 | N3: =COUNTIFS('Daily Order Tracker'!$F$4:$F$93,$A3,'Daily Order Tracker'!$R$4:$R$93,12) -> 0 | O3: =COUNTIFS('Daily Order Tracker'!$F$4:$F$93,$A3,'Daily Order Tracker'!$R$4:$R$93,13) -> 0 | P3: =COUNTIFS('Daily Order Tracker'!$F$4:$F$93,$A3,'Daily Order Tracker'!$R$4:$R$93,14) -> 0 | Q3: =COUNTIFS('Daily Order Tracker'!$F$4:$F$93,$A3,'Daily Order Tracker'!$R$4:$R$93,15) -> 2 | R3: =COUNTIFS('Daily Order Tracker'!$F$4:$F$93,$A3,'Daily Order Tracker'!$R$4:$R$93,16) -> 1 | S3: =COUNTIFS('Daily Order Tracker'!$F$4:$F$93,$A3,'Daily Order Tracker'!$R$4:$R$93,17) -> 0 | T3: =COUNTIFS('Daily Order Tracker'!$F$4:$F$93,$A3,'Daily Order Tracker'!$R$4:$R$93,18) -> 0 | U3: =COUNTIFS('Daily Order Tracker'!$F$4:$F$93,$A3,'Daily Order Tracker'!$R$4:$R$93,19) -> 1 | V3: =COUNTIFS('Daily Order Tracker'!$F$4:$F$93,$A3,'Daily Order Tracker'!$R$4:$R$93,20) -> 1 | W3: =COUNTIFS('Daily Order Tracker'!$F$4:$F$93,$A3,'Daily Order Tracker'!$R$4:$R$93,21) -> 1 | X3: =COUNTIFS('Daily Order Tracker'!$F$4:$F$93,$A3,'Daily Order Tracker'!$R$4:$R$93,22) -> 0 | Y3: =COUNTIFS('Daily Order Tracker'!$F$4:$F$93,$A3,'Daily Order Tracker'!$R$4:$R$93,23) -> 0 | Z3: =MAX(B3:Y3) -> 2 | AA3: =SUM(B3:E3) -> 0 | AB3: =SUM(F3:I3) -> 0 | AC3: =SUM(J3:M3) -> 3 | AD3: =SUM(N3:Q3) -> 2 | AE3: =SUM(R3:U3) -> 2 | AF3: =SUM(V3:Y3) -> 2
A4: Swish Kitchen - Indiranagar | B4: =COUNTIFS('Daily Order Tracker'!$F$4:$F$93,$A4,'Daily Order Tracker'!$R$4:$R$93,0) -> 0 | C4: =COUNTIFS('Daily Order Tracker'!$F$4:$F$93,$A4,'Daily Order Tracker'!$R$4:$R$93,1) -> 0 | D4: =COUNTIFS('Daily Order Tracker'!$F$4:$F$93,$A4,'Daily Order Tracker'!$R$4:$R$93,2) -> 0 | E4: =COUNTIFS('Daily Order Tracker'!$F$4:$F$93,$A4,'Daily Order Tracker'!$R$4:$R$93,3) -> 0 | F4: =COUNTIFS('Daily Order Tracker'!$F$4:$F$93,$A4,'Daily Order Tracker'!$R$4:$R$93,4) -> 0 | G4: =COUNTIFS('Daily Order Tracker'!$F$4:$F$93,$A4,'Daily Order Tracker'!$R$4:$R$93,5) -> 0 | H4: =COUNTIFS('Daily Order Tracker'!$F$4:$F$93,$A4,'Daily Order Tracker'!$R$4:$R$93,6) -> 0 | I4: =COUNTIFS('Daily Order Tracker'!$F$4:$F$93,$A4,'Daily Order Tracker'!$R$4:$R$93,7) -> 0 | J4: =COUNTIFS('Daily Order Tracker'!$F$4:$F$93,$A4,'Daily Order Tracker'!$R$4:$R$93,8) -> 1 | K4: =COUNTIFS('Daily Order Tracker'!$F$4:$F$93,$A4,'Daily Order Tracker'!$R$4:$R$93,9) -> 0 | L4: =COUNTIFS('Daily Order Tracker'!$F$4:$F$93,$A4,'Daily Order Tracker'!$R$4:$R$93,10) -> 1 | M4: =COUNTIFS('Daily Order Tracker'!$F$4:$F$93,$A4,'Daily Order Tracker'!$R$4:$R$93,11) -> 0 | N4: =COUNTIFS('Daily Order Tracker'!$F$4:$F$93,$A4,'Daily Order Tracker'!$R$4:$R$93,12) -> 1 | O4: =COUNTIFS('Daily Order Tracker'!$F$4:$F$93,$A4,'Daily Order Tracker'!$R$4:$R$93,13) -> 0 | P4: =COUNTIFS('Daily Order Tracker'!$F$4:$F$93,$A4,'Daily Order Tracker'!$R$4:$R$93,14) -> 0 | Q4: =COUNTIFS('Daily Order Tracker'!$F$4:$F$93,$A4,'Daily Order Tracker'!$R$4:$R$93,15) -> 0 | R4: =COUNTIFS('Daily Order Tracker'!$F$4:$F$93,$A4,'Daily Order Tracker'!$R$4:$R$93,16) -> 0 | S4: =COUNTIFS('Daily Order Tracker'!$F$4:$F$93,$A4,'Daily Order Tracker'!$R$4:$R$93,17) -> 0 | T4: =COUNTIFS('Daily Order Tracker'!$F$4:$F$93,$A4,'Daily Order Tracker'!$R$4:$R$93,18) -> 3 | U4: =COUNTIFS('Daily Order Tracker'!$F$4:$F$93,$A4,'Daily Order Tracker'!$R$4:$R$93,19) -> 3 | V4: =COUNTIFS('Daily Order Tracker'!$F$4:$F$93,$A4,'Daily Order Tracker'!$R$4:$R$93,20) -> 0 | W4: =COUNTIFS('Daily Order Tracker'!$F$4:$F$93,$A4,'Daily Order Tracker'!$R$4:$R$93,21) -> 0 | X4: =COUNTIFS('Daily Order Tracker'!$F$4:$F$93,$A4,'Daily Order Tracker'!$R$4:$R$93,22) -> 0 | Y4: =COUNTIFS('Daily Order Tracker'!$F$4:$F$93,$A4,'Daily Order Tracker'!$R$4:$R$93,23) -> 0 | Z4: =MAX(B4:Y4) -> 3 | AA4: =SUM(B4:E4) -> 0 | AB4: =SUM(F4:I4) -> 0 | AC4: =SUM(J4:M4) -> 2 | AD4: =SUM(N4:Q4) -> 1 | AE4: =SUM(R4:U4) -> 6 | AF4: =SUM(V4:Y4) -> 0
A5: Swish Kitchen - Whitefield | B5: =COUNTIFS('Daily Order Tracker'!$F$4:$F$93,$A5,'Daily Order Tracker'!$R$4:$R$93,0) -> 0 | C5: =COUNTIFS('Daily Order Tracker'!$F$4:$F$93,$A5,'Daily Order Tracker'!$R$4:$R$93,1) -> 0 | D5: =COUNTIFS('Daily Order Tracker'!$F$4:$F$93,$A5,'Daily Order Tracker'!$R$4:$R$93,2) -> 0 | E5: =COUNTIFS('Daily Order Tracker'!$F$4:$F$93,$A5,'Daily Order Tracker'!$R$4:$R$93,3) -> 0 | F5: =COUNTIFS('Daily Order Tracker'!$F$4:$F$93,$A5,'Daily Order Tracker'!$R$4:$R$93,4) -> 0 | G5: =COUNTIFS('Daily Order Tracker'!$F$4:$F$93,$A5,'Daily Order Tracker'!$R$4:$R$93,5) -> 0 | H5: =COUNTIFS('Daily Order Tracker'!$F$4:$F$93,$A5,'Daily Order Tracker'!$R$4:$R$93,6) -> 0 | I5: =COUNTIFS('Daily Order Tracker'!$F$4:$F$93,$A5,'Daily Order Tracker'!$R$4:$R$93,7) -> 0 | J5: =COUNTIFS('Daily Order Tracker'!$F$4:$F$93,$A5,'Daily Order Tracker'!$R$4:$R$93,8) -> 0 | K5: =COUNTIFS('Daily Order Tracker'!$F$4:$F$93,$A5,'Daily Order Tracker'!$R$4:$R$93,9) -> 1 | L5: =COUNTIFS('Daily Order Tracker'!$F$4:$F$93,$A5,'Daily Order Tracker'!$R$4:$R$93,10) -> 2 | M5: =COUNTIFS('Daily Order Tracker'!$F$4:$F$93,$A5,'Daily Order Tracker'!$R$4:$R$93,11) -> 1 | N5: =COUNTIFS('Daily Order Tracker'!$F$4:$F$93,$A5,'Daily Order Tracker'!$R$4:$R$93,12) -> 0 | O5: =COUNTIFS('Daily Order Tracker'!$F$4:$F$93,$A5,'Daily Order Tracker'!$R$4:$R$93,13) -> 1 | P5: =COUNTIFS('Daily Order Tracker'!$F$4:$F$93,$A5,'Daily Order Tracker'!$R$4:$R$93,14) -> 0 | Q5: =COUNTIFS('Daily Order Tracker'!$F$4:$F$93,$A5,'Daily Order Tracker'!$R$4:$R$93,15) -> 1 | R5: =COUNTIFS('Daily Order Tracker'!$F$4:$F$93,$A5,'Daily Order Tracker'!$R$4:$R$93,16) -> 1 | S5: =COUNTIFS('Daily Order Tracker'!$F$4:$F$93,$A5,'Daily Order Tracker'!$R$4:$R$93,17) -> 0 | T5: =COUNTIFS('Daily Order Tracker'!$F$4:$F$93,$A5,'Daily Order Tracker'!$R$4:$R$93,18) -> 1 | U5: =COUNTIFS('Daily Order Tracker'!$F$4:$F$93,$A5,'Daily Order Tracker'!$R$4:$R$93,19) -> 0 | V5: =COUNTIFS('Daily Order Tracker'!$F$4:$F$93,$A5,'Daily Order Tracker'!$R$4:$R$93,20) -> 0 | W5: =COUNTIFS('Daily Order Tracker'!$F$4:$F$93,$A5,'Daily Order Tracker'!$R$4:$R$93,21) -> 1 | X5: =COUNTIFS('Daily Order Tracker'!$F$4:$F$93,$A5,'Daily Order Tracker'!$R$4:$R$93,22) -> 0 | Y5: =COUNTIFS('Daily Order Tracker'!$F$4:$F$93,$A5,'Daily Order Tracker'!$R$4:$R$93,23) -> 0 | Z5: =MAX(B5:Y5) -> 2 | AA5: =SUM(B5:E5) -> 0 | AB5: =SUM(F5:I5) -> 0 | AC5: =SUM(J5:M5) -> 4 | AD5: =SUM(N5:Q5) -> 2 | AE5: =SUM(R5:U5) -> 2 | AF5: =SUM(V5:Y5) -> 1
A6: Swish Kitchen - Electronic City | B6: =COUNTIFS('Daily Order Tracker'!$F$4:$F$93,$A6,'Daily Order Tracker'!$R$4:$R$93,0) -> 0 | C6: =COUNTIFS('Daily Order Tracker'!$F$4:$F$93,$A6,'Daily Order Tracker'!$R$4:$R$93,1) -> 0 | D6: =COUNTIFS('Daily Order Tracker'!$F$4:$F$93,$A6,'Daily Order Tracker'!$R$4:$R$93,2) -> 0 | E6: =COUNTIFS('Daily Order Tracker'!$F$4:$F$93,$A6,'Daily Order Tracker'!$R$4:$R$93,3) -> 0 | F6: =COUNTIFS('Daily Order Tracker'!$F$4:$F$93,$A6,'Daily Order Tracker'!$R$4:$R$93,4) -> 0 | G6: =COUNTIFS('Daily Order Tracker'!$F$4:$F$93,$A6,'Daily Order Tracker'!$R$4:$R$93,5) -> 0 | H6: =COUNTIFS('Daily Order Tracker'!$F$4:$F$93,$A6,'Daily Order Tracker'!$R$4:$R$93,6) -> 0 | I6: =COUNTIFS('Daily Order Tracker'!$F$4:$F$93,$A6,'Daily Order Tracker'!$R$4:$R$93,7) -> 0 | J6: =COUNTIFS('Daily Order Tracker'!$F$4:$F$93,$A6,'Daily Order Tracker'!$R$4:$R$93,8) -> 0 | K6: =COUNTIFS('Daily Order Tracker'!$F$4:$F$93,$A6,'Daily Order Tracker'!$R$4:$R$93,9) -> 2 | L6: =COUNTIFS('Daily Order Tracker'!$F$4:$F$93,$A6,'Daily Order Tracker'!$R$4:$R$93,10) -> 1 | M6: =COUNTIFS('Daily Order Tracker'!$F$4:$F$93,$A6,'Daily Order Tracker'!$R$4:$R$93,11) -> 1 | N6: =COUNTIFS('Daily Order Tracker'!$F$4:$F$93,$A6,'Daily Order Tracker'!$R$4:$R$93,12) -> 1 | O6: =COUNTIFS('Daily Order Tracker'!$F$4:$F$93,$A6,'Daily Order Tracker'!$R$4:$R$93,13) -> 1 | P6: =COUNTIFS('Daily Order Tracker'!$F$4:$F$93,$A6,'Daily Order Tracker'!$R$4:$R$93,14) -> 0 | Q6: =COUNTIFS('Daily Order Tracker'!$F$4:$F$93,$A6,'Daily Order Tracker'!$R$4:$R$93,15) -> 1 | R6: =COUNTIFS('Daily Order Tracker'!$F$4:$F$93,$A6,'Daily Order Tracker'!$R$4:$R$93,16) -> 1 | S6: =COUNTIFS('Daily Order Tracker'!$F$4:$F$93,$A6,'Daily Order Tracker'!$R$4:$R$93,17) -> 0 | T6: =COUNTIFS('Daily Order Tracker'!$F$4:$F$93,$A6,'Daily Order Tracker'!$R$4:$R$93,18) -> 0 | U6: =COUNTIFS('Daily Order Tracker'!$F$4:$F$93,$A6,'Daily Order Tracker'!$R$4:$R$93,19) -> 0 | V6: =COUNTIFS('Daily Order Tracker'!$F$4:$F$93,$A6,'Daily Order Tracker'!$R$4:$R$93,20) -> 0 | W6: =COUNTIFS('Daily Order Tracker'!$F$4:$F$93,$A6,'Daily Order Tracker'!$R$4:$R$93,21) -> 1 | X6: =COUNTIFS('Daily Order Tracker'!$F$4:$F$93,$A6,'Daily Order Tracker'!$R$4:$R$93,22) -> 0 | Y6: =COUNTIFS('Daily Order Tracker'!$F$4:$F$93,$A6,'Daily Order Tracker'!$R$4:$R$93,23) -> 0 | Z6: =MAX(B6:Y6) -> 2 | AA6: =SUM(B6:E6) -> 0 | AB6: =SUM(F6:I6) -> 0 | AC6: =SUM(J6:M6) -> 4 | AD6: =SUM(N6:Q6) -> 3 | AE6: =SUM(R6:U6) -> 1 | AF6: =SUM(V6:Y6) -> 1
A7: Swish Kitchen - Marathahalli | B7: =COUNTIFS('Daily Order Tracker'!$F$4:$F$93,$A7,'Daily Order Tracker'!$R$4:$R$93,0) -> 0 | C7: =COUNTIFS('Daily Order Tracker'!$F$4:$F$93,$A7,'Daily Order Tracker'!$R$4:$R$93,1) -> 0 | D7: =COUNTIFS('Daily Order Tracker'!$F$4:$F$93,$A7,'Daily Order Tracker'!$R$4:$R$93,2) -> 0 | E7: =COUNTIFS('Daily Order Tracker'!$F$4:$F$93,$A7,'Daily Order Tracker'!$R$4:$R$93,3) -> 0 | F7: =COUNTIFS('Daily Order Tracker'!$F$4:$F$93,$A7,'Daily Order Tracker'!$R$4:$R$93,4) -> 0 | G7: =COUNTIFS('Daily Order Tracker'!$F$4:$F$93,$A7,'Daily Order Tracker'!$R$4:$R$93,5) -> 0 | H7: =COUNTIFS('Daily Order Tracker'!$F$4:$F$93,$A7,'Daily Order Tracker'!$R$4:$R$93,6) -> 0 | I7: =COUNTIFS('Daily Order Tracker'!$F$4:$F$93,$A7,'Daily Order Tracker'!$R$4:$R$93,7) -> 0 | J7: =COUNTIFS('Daily Order Tracker'!$F$4:$F$93,$A7,'Daily Order Tracker'!$R$4:$R$93,8) -> 3 | K7: =COUNTIFS('Daily Order Tracker'!$F$4:$F$93,$A7,'Daily Order Tracker'!$R$4:$R$93,9) -> 0 | L7: =COUNTIFS('Daily Order Tracker'!$F$4:$F$93,$A7,'Daily Order Tracker'!$R$4:$R$93,10) -> 0 | M7: =COUNTIFS('Daily Order Tracker'!$F$4:$F$93,$A7,'Daily Order Tracker'!$R$4:$R$93,11) -> 0 | N7: =COUNTIFS('Daily Order Tracker'!$F$4:$F$93,$A7,'Daily Order Tracker'!$R$4:$R$93,12) -> 0 | O7: =COUNTIFS('Daily Order Tracker'!$F$4:$F$93,$A7,'Daily Order Tracker'!$R$4:$R$93,13) -> 0 | P7: =COUNTIFS('Daily Order Tracker'!$F$4:$F$93,$A7,'Daily Order Tracker'!$R$4:$R$93,14) -> 1 | Q7: =COUNTIFS('Daily Order Tracker'!$F$4:$F$93,$A7,'Daily Order Tracker'!$R$4:$R$93,15) -> 0 | R7: =COUNTIFS('Daily Order Tracker'!$F$4:$F$93,$A7,'Daily Order Tracker'!$R$4:$R$93,16) -> 2 | S7: =COUNTIFS('Daily Order Tracker'!$F$4:$F$93,$A7,'Daily Order Tracker'!$R$4:$R$93,17) -> 1 | T7: =COUNTIFS('Daily Order Tracker'!$F$4:$F$93,$A7,'Daily Order Tracker'!$R$4:$R$93,18) -> 1 | U7: =COUNTIFS('Daily Order Tracker'!$F$4:$F$93,$A7,'Daily Order Tracker'!$R$4:$R$93,19) -> 0 | V7: =COUNTIFS('Daily Order Tracker'!$F$4:$F$93,$A7,'Daily Order Tracker'!$R$4:$R$93,20) -> 0 | W7: =COUNTIFS('Daily Order Tracker'!$F$4:$F$93,$A7,'Daily Order Tracker'!$R$4:$R$93,21) -> 1 | X7: =COUNTIFS('Daily Order Tracker'!$F$4:$F$93,$A7,'Daily Order Tracker'!$R$4:$R$93,22) -> 0 | Y7: =COUNTIFS('Daily Order Tracker'!$F$4:$F$93,$A7,'Daily Order Tracker'!$R$4:$R$93,23) -> 0 | Z7: =MAX(B7:Y7) -> 3 | AA7: =SUM(B7:E7) -> 0 | AB7: =SUM(F7:I7) -> 0 | AC7: =SUM(J7:M7) -> 3 | AD7: =SUM(N7:Q7) -> 1 | AE7: =SUM(R7:U7) -> 4 | AF7: =SUM(V7:Y7) -> 1
A8: Swish Kitchen - JP Nagar | B8: =COUNTIFS('Daily Order Tracker'!$F$4:$F$93,$A8,'Daily Order Tracker'!$R$4:$R$93,0) -> 0 | C8: =COUNTIFS('Daily Order Tracker'!$F$4:$F$93,$A8,'Daily Order Tracker'!$R$4:$R$93,1) -> 0 | D8: =COUNTIFS('Daily Order Tracker'!$F$4:$F$93,$A8,'Daily Order Tracker'!$R$4:$R$93,2) -> 0 | E8: =COUNTIFS('Daily Order Tracker'!$F$4:$F$93,$A8,'Daily Order Tracker'!$R$4:$R$93,3) -> 0 | F8: =COUNTIFS('Daily Order Tracker'!$F$4:$F$93,$A8,'Daily Order Tracker'!$R$4:$R$93,4) -> 0 | G8: =COUNTIFS('Daily Order Tracker'!$F$4:$F$93,$A8,'Daily Order Tracker'!$R$4:$R$93,5) -> 0 | H8: =COUNTIFS('Daily Order Tracker'!$F$4:$F$93,$A8,'Daily Order Tracker'!$R$4:$R$93,6) -> 0 | I8: =COUNTIFS('Daily Order Tracker'!$F$4:$F$93,$A8,'Daily Order Tracker'!$R$4:$R$93,7) -> 0 | J8: =COUNTIFS('Daily Order Tracker'!$F$4:$F$93,$A8,'Daily Order Tracker'!$R$4:$R$93,8) -> 0 | K8: =COUNTIFS('Daily Order Tracker'!$F$4:$F$93,$A8,'Daily Order Tracker'!$R$4:$R$93,9) -> 1 | L8: =COUNTIFS('Daily Order Tracker'!$F$4:$F$93,$A8,'Daily Order Tracker'!$R$4:$R$93,10) -> 0 | M8: =COUNTIFS('Daily Order Tracker'!$F$4:$F$93,$A8,'Daily Order Tracker'!$R$4:$R$93,11) -> 0 | N8: =COUNTIFS('Daily Order Tracker'!$F$4:$F$93,$A8,'Daily Order Tracker'!$R$4:$R$93,12) -> 0 | O8: =COUNTIFS('Daily Order Tracker'!$F$4:$F$93,$A8,'Daily Order Tracker'!$R$4:$R$93,13) -> 1 | P8: =COUNTIFS('Daily Order Tracker'!$F$4:$F$93,$A8,'Daily Order Tracker'!$R$4:$R$93,14) -> 2 | Q8: =COUNTIFS('Daily Order Tracker'!$F$4:$F$93,$A8,'Daily Order Tracker'!$R$4:$R$93,15) -> 1 | R8: =COUNTIFS('Daily Order Tracker'!$F$4:$F$93,$A8,'Daily Order Tracker'!$R$4:$R$93,16) -> 0 | S8: =COUNTIFS('Daily Order Tracker'!$F$4:$F$93,$A8,'Daily Order Tracker'!$R$4:$R$93,17) -> 2 | T8: =COUNTIFS('Daily Order Tracker'!$F$4:$F$93,$A8,'Daily Order Tracker'!$R$4:$R$93,18) -> 1 | U8: =COUNTIFS('Daily Order Tracker'!$F$4:$F$93,$A8,'Daily Order Tracker'!$R$4:$R$93,19) -> 0 | V8: =COUNTIFS('Daily Order Tracker'!$F$4:$F$93,$A8,'Daily Order Tracker'!$R$4:$R$93,20) -> 0 | W8: =COUNTIFS('Daily Order Tracker'!$F$4:$F$93,$A8,'Daily Order Tracker'!$R$4:$R$93,21) -> 1 | X8: =COUNTIFS('Daily Order Tracker'!$F$4:$F$93,$A8,'Daily Order Tracker'!$R$4:$R$93,22) -> 0 | Y8: =COUNTIFS('Daily Order Tracker'!$F$4:$F$93,$A8,'Daily Order Tracker'!$R$4:$R$93,23) -> 0 | Z8: =MAX(B8:Y8) -> 2 | AA8: =SUM(B8:E8) -> 0 | AB8: =SUM(F8:I8) -> 0 | AC8: =SUM(J8:M8) -> 1 | AD8: =SUM(N8:Q8) -> 4 | AE8: =SUM(R8:U8) -> 3 | AF8: =SUM(V8:Y8) -> 1
A9: Swish Kitchen - BTM Layout | B9: =COUNTIFS('Daily Order Tracker'!$F$4:$F$93,$A9,'Daily Order Tracker'!$R$4:$R$93,0) -> 0 | C9: =COUNTIFS('Daily Order Tracker'!$F$4:$F$93,$A9,'Daily Order Tracker'!$R$4:$R$93,1) -> 0 | D9: =COUNTIFS('Daily Order Tracker'!$F$4:$F$93,$A9,'Daily Order Tracker'!$R$4:$R$93,2) -> 0 | E9: =COUNTIFS('Daily Order Tracker'!$F$4:$F$93,$A9,'Daily Order Tracker'!$R$4:$R$93,3) -> 0 | F9: =COUNTIFS('Daily Order Tracker'!$F$4:$F$93,$A9,'Daily Order Tracker'!$R$4:$R$93,4) -> 0 | G9: =COUNTIFS('Daily Order Tracker'!$F$4:$F$93,$A9,'Daily Order Tracker'!$R$4:$R$93,5) -> 0 | H9: =COUNTIFS('Daily Order Tracker'!$F$4:$F$93,$A9,'Daily Order Tracker'!$R$4:$R$93,6) -> 0 | I9: =COUNTIFS('Daily Order Tracker'!$F$4:$F$93,$A9,'Daily Order Tracker'!$R$4:$R$93,7) -> 0 | J9: =COUNTIFS('Daily Order Tracker'!$F$4:$F$93,$A9,'Daily Order Tracker'!$R$4:$R$93,8) -> 0 | K9: =COUNTIFS('Daily Order Tracker'!$F$4:$F$93,$A9,'Daily Order Tracker'!$R$4:$R$93,9) -> 0 | L9: =COUNTIFS('Daily Order Tracker'!$F$4:$F$93,$A9,'Daily Order Tracker'!$R$4:$R$93,10) -> 1 | M9: =COUNTIFS('Daily Order Tracker'!$F$4:$F$93,$A9,'Daily Order Tracker'!$R$4:$R$93,11) -> 2 | N9: =COUNTIFS('Daily Order Tracker'!$F$4:$F$93,$A9,'Daily Order Tracker'!$R$4:$R$93,12) -> 0 | O9: =COUNTIFS('Daily Order Tracker'!$F$4:$F$93,$A9,'Daily Order Tracker'!$R$4:$R$93,13) -> 0 | P9: =COUNTIFS('Daily Order Tracker'!$F$4:$F$93,$A9,'Daily Order Tracker'!$R$4:$R$93,14) -> 1 | Q9: =COUNTIFS('Daily Order Tracker'!$F$4:$F$93,$A9,'Daily Order Tracker'!$R$4:$R$93,15) -> 0 | R9: =COUNTIFS('Daily Order Tracker'!$F$4:$F$93,$A9,'Daily Order Tracker'!$R$4:$R$93,16) -> 0 | S9: =COUNTIFS('Daily Order Tracker'!$F$4:$F$93,$A9,'Daily Order Tracker'!$R$4:$R$93,17) -> 1 | T9: =COUNTIFS('Daily Order Tracker'!$F$4:$F$93,$A9,'Daily Order Tracker'!$R$4:$R$93,18) -> 0 | U9: =COUNTIFS('Daily Order Tracker'!$F$4:$F$93,$A9,'Daily Order Tracker'!$R$4:$R$93,19) -> 1 | V9: =COUNTIFS('Daily Order Tracker'!$F$4:$F$93,$A9,'Daily Order Tracker'!$R$4:$R$93,20) -> 2 | W9: =COUNTIFS('Daily Order Tracker'!$F$4:$F$93,$A9,'Daily Order Tracker'!$R$4:$R$93,21) -> 1 | X9: =COUNTIFS('Daily Order Tracker'!$F$4:$F$93,$A9,'Daily Order Tracker'!$R$4:$R$93,22) -> 0 | Y9: =COUNTIFS('Daily Order Tracker'!$F$4:$F$93,$A9,'Daily Order Tracker'!$R$4:$R$93,23) -> 0 | Z9: =MAX(B9:Y9) -> 2 | AA9: =SUM(B9:E9) -> 0 | AB9: =SUM(F9:I9) -> 0 | AC9: =SUM(J9:M9) -> 3 | AD9: =SUM(N9:Q9) -> 1 | AE9: =SUM(R9:U9) -> 2 | AF9: =SUM(V9:Y9) -> 3
A10: Swish Kitchen - Bellandur | B10: =COUNTIFS('Daily Order Tracker'!$F$4:$F$93,$A10,'Daily Order Tracker'!$R$4:$R$93,0) -> 0 | C10: =COUNTIFS('Daily Order Tracker'!$F$4:$F$93,$A10,'Daily Order Tracker'!$R$4:$R$93,1) -> 0 | D10: =COUNTIFS('Daily Order Tracker'!$F$4:$F$93,$A10,'Daily Order Tracker'!$R$4:$R$93,2) -> 0 | E10: =COUNTIFS('Daily Order Tracker'!$F$4:$F$93,$A10,'Daily Order Tracker'!$R$4:$R$93,3) -> 0 | F10: =COUNTIFS('Daily Order Tracker'!$F$4:$F$93,$A10,'Daily Order Tracker'!$R$4:$R$93,4) -> 0 | G10: =COUNTIFS('Daily Order Tracker'!$F$4:$F$93,$A10,'Daily Order Tracker'!$R$4:$R$93,5) -> 0 | H10: =COUNTIFS('Daily Order Tracker'!$F$4:$F$93,$A10,'Daily Order Tracker'!$R$4:$R$93,6) -> 0 | I10: =COUNTIFS('Daily Order Tracker'!$F$4:$F$93,$A10,'Daily Order Tracker'!$R$4:$R$93,7) -> 0 | J10: =COUNTIFS('Daily Order Tracker'!$F$4:$F$93,$A10,'Daily Order Tracker'!$R$4:$R$93,8) -> 0 | K10: =COUNTIFS('Daily Order Tracker'!$F$4:$F$93,$A10,'Daily Order Tracker'!$R$4:$R$93,9) -> 0 | L10: =COUNTIFS('Daily Order Tracker'!$F$4:$F$93,$A10,'Daily Order Tracker'!$R$4:$R$93,10) -> 1 | M10: =COUNTIFS('Daily Order Tracker'!$F$4:$F$93,$A10,'Daily Order Tracker'!$R$4:$R$93,11) -> 1 | N10: =COUNTIFS('Daily Order Tracker'!$F$4:$F$93,$A10,'Daily Order Tracker'!$R$4:$R$93,12) -> 0 | O10: =COUNTIFS('Daily Order Tracker'!$F$4:$F$93,$A10,'Daily Order Tracker'!$R$4:$R$93,13) -> 1 | P10: =COUNTIFS('Daily Order Tracker'!$F$4:$F$93,$A10,'Daily Order Tracker'!$R$4:$R$93,14) -> 0 | Q10: =COUNTIFS('Daily Order Tracker'!$F$4:$F$93,$A10,'Daily Order Tracker'!$R$4:$R$93,15) -> 0 | R10: =COUNTIFS('Daily Order Tracker'!$F$4:$F$93,$A10,'Daily Order Tracker'!$R$4:$R$93,16) -> 2 | S10: =COUNTIFS('Daily Order Tracker'!$F$4:$F$93,$A10,'Daily Order Tracker'!$R$4:$R$93,17) -> 1 | T10: =COUNTIFS('Daily Order Tracker'!$F$4:$F$93,$A10,'Daily Order Tracker'!$R$4:$R$93,18) -> 2 | U10: =COUNTIFS('Daily Order Tracker'!$F$4:$F$93,$A10,'Daily Order Tracker'!$R$4:$R$93,19) -> 0 | V10: =COUNTIFS('Daily Order Tracker'!$F$4:$F$93,$A10,'Daily Order Tracker'!$R$4:$R$93,20) -> 0 | W10: =COUNTIFS('Daily Order Tracker'!$F$4:$F$93,$A10,'Daily Order Tracker'!$R$4:$R$93,21) -> 1 | X10: =COUNTIFS('Daily Order Tracker'!$F$4:$F$93,$A10,'Daily Order Tracker'!$R$4:$R$93,22) -> 0 | Y10: =COUNTIFS('Daily Order Tracker'!$F$4:$F$93,$A10,'Daily Order Tracker'!$R$4:$R$93,23) -> 0 | Z10: =MAX(B10:Y10) -> 2 | AA10: =SUM(B10:E10) -> 0 | AB10: =SUM(F10:I10) -> 0 | AC10: =SUM(J10:M10) -> 2 | AD10: =SUM(N10:Q10) -> 1 | AE10: =SUM(R10:U10) -> 5 | AF10: =SUM(V10:Y10) -> 1
A11: Swish Kitchen - Sarjapur | B11: =COUNTIFS('Daily Order Tracker'!$F$4:$F$93,$A11,'Daily Order Tracker'!$R$4:$R$93,0) -> 0 | C11: =COUNTIFS('Daily Order Tracker'!$F$4:$F$93,$A11,'Daily Order Tracker'!$R$4:$R$93,1) -> 0 | D11: =COUNTIFS('Daily Order Tracker'!$F$4:$F$93,$A11,'Daily Order Tracker'!$R$4:$R$93,2) -> 0 | E11: =COUNTIFS('Daily Order Tracker'!$F$4:$F$93,$A11,'Daily Order Tracker'!$R$4:$R$93,3) -> 0 | F11: =COUNTIFS('Daily Order Tracker'!$F$4:$F$93,$A11,'Daily Order Tracker'!$R$4:$R$93,4) -> 0 | G11: =COUNTIFS('Daily Order Tracker'!$F$4:$F$93,$A11,'Daily Order Tracker'!$R$4:$R$93,5) -> 0 | H11: =COUNTIFS('Daily Order Tracker'!$F$4:$F$93,$A11,'Daily Order Tracker'!$R$4:$R$93,6) -> 0 | I11: =COUNTIFS('Daily Order Tracker'!$F$4:$F$93,$A11,'Daily Order Tracker'!$R$4:$R$93,7) -> 0 | J11: =COUNTIFS('Daily Order Tracker'!$F$4:$F$93,$A11,'Daily Order Tracker'!$R$4:$R$93,8) -> 0 | K11: =COUNTIFS('Daily Order Tracker'!$F$4:$F$93,$A11,'Daily Order Tracker'!$R$4:$R$93,9) -> 0 | L11: =COUNTIFS('Daily Order Tracker'!$F$4:$F$93,$A11,'Daily Order Tracker'!$R$4:$R$93,10) -> 2 | M11: =COUNTIFS('Daily Order Tracker'!$F$4:$F$93,$A11,'Daily Order Tracker'!$R$4:$R$93,11) -> 0 | N11: =COUNTIFS('Daily Order Tracker'!$F$4:$F$93,$A11,'Daily Order Tracker'!$R$4:$R$93,12) -> 2 | O11: =COUNTIFS('Daily Order Tracker'!$F$4:$F$93,$A11,'Daily Order Tracker'!$R$4:$R$93,13) -> 0 | P11: =COUNTIFS('Daily Order Tracker'!$F$4:$F$93,$A11,'Daily Order Tracker'!$R$4:$R$93,14) -> 0 | Q11: =COUNTIFS('Daily Order Tracker'!$F$4:$F$93,$A11,'Daily Order Tracker'!$R$4:$R$93,15) -> 0 | R11: =COUNTIFS('Daily Order Tracker'!$F$4:$F$93,$A11,'Daily Order Tracker'!$R$4:$R$93,16) -> 2 | S11: =COUNTIFS('Daily Order Tracker'!$F$4:$F$93,$A11,'Daily Order Tracker'!$R$4:$R$93,17) -> 0 | T11: =COUNTIFS('Daily Order Tracker'!$F$4:$F$93,$A11,'Daily Order Tracker'!$R$4:$R$93,18) -> 0 | U11: =COUNTIFS('Daily Order Tracker'!$F$4:$F$93,$A11,'Daily Order Tracker'!$R$4:$R$93,19) -> 1 | V11: =COUNTIFS('Daily Order Tracker'!$F$4:$F$93,$A11,'Daily Order Tracker'!$R$4:$R$93,20) -> 0 | W11: =COUNTIFS('Daily Order Tracker'!$F$4:$F$93,$A11,'Daily Order Tracker'!$R$4:$R$93,21) -> 2 | X11: =COUNTIFS('Daily Order Tracker'!$F$4:$F$93,$A11,'Daily Order Tracker'!$R$4:$R$93,22) -> 0 | Y11: =COUNTIFS('Daily Order Tracker'!$F$4:$F$93,$A11,'Daily Order Tracker'!$R$4:$R$93,23) -> 0 | Z11: =MAX(B11:Y11) -> 2 | AA11: =SUM(B11:E11) -> 0 | AB11: =SUM(F11:I11) -> 0 | AC11: =SUM(J11:M11) -> 2 | AD11: =SUM(N11:Q11) -> 2 | AE11: =SUM(R11:U11) -> 3 | AF11: =SUM(V11:Y11) -> 2
A12: TOTAL | B12: =SUM(B2:B11) -> 0 | C12: =SUM(C2:C11) -> 0 | D12: =SUM(D2:D11) -> 0 | E12: =SUM(E2:E11) -> 0 | F12: =SUM(F2:F11) -> 0 | G12: =SUM(G2:G11) -> 0 | H12: =SUM(H2:H11) -> 0 | I12: =SUM(I2:I11) -> 0 | ... Y12: =SUM(Y2:Y11) -> 0

Sheet Kitchen Operations Tracker
A1: KITCHEN OPERATIONS TRACKER
A2: Auto-calculated from Daily Order Tracker.
A3: Kitchen Name | B3: Zone | C3: Shift | D3: Chef | E3: Orders Received | F3: Orders Preparing | G3: Orders Ready | H3: Average Prep Time (min) | I3: Delayed Orders | J3: Peak Hour Load | K3: Efficiency %
A4: Swish Kitchen - Koramangala | B4: Koramangala | C4: Morning (7AM-3PM) | D4: Ravi Kumar | E4: =COUNTIF('Daily Order Tracker'!$F$4:$F$93,A4) -> 9 | F4: =COUNTIFS('Daily Order Tracker'!$F$4:$F$93,A4,'Daily Order Tracker'!$N$4:$N$93,"Preparing") -> 1 | G4: =COUNTIFS('Daily Order Tracker'!$F$4:$F$93,A4,'Daily Order Tracker'!$N$4:$N$93,"Ready") -> 0 | H4: =IFERROR(AVERAGEIFS('Daily Order Tracker'!$Q$4:$Q$93,'Daily Order Tracker'!$F$4:$F$93,A4,'Daily Order Tracker'!$Q$4:$Q$93,"<>"),0) -> 4.875 | I4: =COUNTIFS('Daily Order Tracker'!$F$4:$F$93,A4,'Daily Order Tracker'!$S$4:$S$93,"Y") -> 4 | J4: =INDEX(Hourly_Helper!$Z$2:$Z$11,MATCH(A4,Hourly_Helper!$A$2:$A$11,0)) -> 2 | K4: =IFERROR((E4-I4)/E4,0) -> 0.55555556
A5: Swish Kitchen - HSR Layout | B5: HSR Layout | C5: Afternoon (11AM-7PM) | D5: Ananya Rao | E5: =COUNTIF('Daily Order Tracker'!$F$4:$F$93,A5) -> 9 | F5: =COUNTIFS('Daily Order Tracker'!$F$4:$F$93,A5,'Daily Order Tracker'!$N$4:$N$93,"Preparing") -> 0 | G5: =COUNTIFS('Daily Order Tracker'!$F$4:$F$93,A5,'Daily Order Tracker'!$N$4:$N$93,"Ready") -> 0 | H5: =IFERROR(AVERAGEIFS('Daily Order Tracker'!$Q$4:$Q$93,'Daily Order Tracker'!$F$4:$F$93,A5,'Daily Order Tracker'!$Q$4:$Q$93,"<>"),0) -> 6.5 | I5: =COUNTIFS('Daily Order Tracker'!$F$4:$F$93,A5,'Daily Order Tracker'!$S$4:$S$93,"Y") -> 5 | J5: =INDEX(Hourly_Helper!$Z$2:$Z$11,MATCH(A5,Hourly_Helper!$A$2:$A$11,0)) -> 2 | K5: =IFERROR((E5-I5)/E5,0) -> 0.44444444
A6: Swish Kitchen - Indiranagar | B6: Indiranagar | C6: Evening (3PM-11PM) | D6: Suresh Iyer | E6: =COUNTIF('Daily Order Tracker'!$F$4:$F$93,A6) -> 9 | F6: =COUNTIFS('Daily Order Tracker'!$F$4:$F$93,A6,'Daily Order Tracker'!$N$4:$N$93,"Preparing") -> 0 | G6: =COUNTIFS('Daily Order Tracker'!$F$4:$F$93,A6,'Daily Order Tracker'!$N$4:$N$93,"Ready") -> 0 | H6: =IFERROR(AVERAGEIFS('Daily Order Tracker'!$Q$4:$Q$93,'Daily Order Tracker'!$F$4:$F$93,A6,'Daily Order Tracker'!$Q$4:$Q$93,"<>"),0) -> 5.7142857 | I6: =COUNTIFS('Daily Order Tracker'!$F$4:$F$93,A6,'Daily Order Tracker'!$S$4:$S$93,"Y") -> 6 | J6: =INDEX(Hourly_Helper!$Z$2:$Z$11,MATCH(A6,Hourly_Helper!$A$2:$A$11,0)) -> 3 | K6: =IFERROR((E6-I6)/E6,0) -> 0.33333333
A7: Swish Kitchen - Whitefield | B7: Whitefield | C7: Night (6PM-2AM) | D7: Fatima Sheikh | E7: =COUNTIF('Daily Order Tracker'!$F$4:$F$93,A7) -> 9 | F7: =COUNTIFS('Daily Order Tracker'!$F$4:$F$93,A7,'Daily Order Tracker'!$N$4:$N$93,"Preparing") -> 0 | G7: =COUNTIFS('Daily Order Tracker'!$F$4:$F$93,A7,'Daily Order Tracker'!$N$4:$N$93,"Ready") -> 0 | H7: =IFERROR(AVERAGEIFS('Daily Order Tracker'!$Q$4:$Q$93,'Daily Order Tracker'!$F$4:$F$93,A7,'Daily Order Tracker'!$Q$4:$Q$93,"<>"),0) -> 6.2857143 | I7: =COUNTIFS('Daily Order Tracker'!$F$4:$F$93,A7,'Daily Order Tracker'!$S$4:$S$93,"Y") -> 5 | J7: =INDEX(Hourly_Helper!$Z$2:$Z$11,MATCH(A7,Hourly_Helper!$A$2:$A$11,0)) -> 2 | K7: =IFERROR((E7-I7)/E7,0) -> 0.44444444
A8: Swish Kitchen - Electronic City | B8: Electronic City | C8: Morning (7AM-3PM) | D8: Vikram Singh | E8: =COUNTIF('Daily Order Tracker'!$F$4:$F$93,A8) -> 9 | F8: =COUNTIFS('Daily Order Tracker'!$F$4:$F$93,A8,'Daily Order Tracker'!$N$4:$N$93,"Preparing") -> 0 | G8: =COUNTIFS('Daily Order Tracker'!$F$4:$F$93,A8,'Daily Order Tracker'!$N$4:$N$93,"Ready") -> 0 | H8: =IFERROR(AVERAGEIFS('Daily Order Tracker'!$Q$4:$Q$93,'Daily Order Tracker'!$F$4:$F$93,A8,'Daily Order Tracker'!$Q$4:$Q$93,"<>"),0) -> 6.75 | I8: =COUNTIFS('Daily Order Tracker'!$F$4:$F$93,A8,'Daily Order Tracker'!$S$4:$S$93,"Y") -> 8 | J8: =INDEX(Hourly_Helper!$Z$2:$Z$11,MATCH(A8,Hourly_Helper!$A$2:$A$11,0)) -> 2 | K8: =IFERROR((E8-I8)/E8,0) -> 0.11111111
A9: Swish Kitchen - Marathahalli | B9: Marathahalli | C9: Afternoon (11AM-7PM) | D9: Deepa Nair | E9: =COUNTIF('Daily Order Tracker'!$F$4:$F$93,A9) -> 9 | F9: =COUNTIFS('Daily Order Tracker'!$F$4:$F$93,A9,'Daily Order Tracker'!$N$4:$N$93,"Preparing") -> 0 | G9: =COUNTIFS('Daily Order Tracker'!$F$4:$F$93,A9,'Daily Order Tracker'!$N$4:$N$93,"Ready") -> 1 | H9: =IFERROR(AVERAGEIFS('Daily Order Tracker'!$Q$4:$Q$93,'Daily Order Tracker'!$F$4:$F$93,A9,'Daily Order Tracker'!$Q$4:$Q$93,"<>"),0) -> 5.3333333 | I9: =COUNTIFS('Daily Order Tracker'!$F$4:$F$93,A9,'Daily Order Tracker'!$S$4:$S$93,"Y") -> 3 | J9: =INDEX(Hourly_Helper!$Z$2:$Z$11,MATCH(A9,Hourly_Helper!$A$2:$A$11,0)) -> 3 | K9: =IFERROR((E9-I9)/E9,0) -> 0.66666667
A10: Swish Kitchen - JP Nagar | B10: JP Nagar | C10: Evening (3PM-11PM) | D10: Arjun Reddy | E10: =COUNTIF('Daily Order Tracker'!$F$4:$F$93,A10) -> 9 | F10: =COUNTIFS('Daily Order Tracker'!$F$4:$F$93,A10,'Daily Order Tracker'!$N$4:$N$93,"Preparing") -> 1 | G10: =COUNTIFS('Daily Order Tracker'!$F$4:$F$93,A10,'Daily Order Tracker'!$N$4:$N$93,"Ready") -> 0 | H10: =IFERROR(AVERAGEIFS('Daily Order Tracker'!$Q$4:$Q$93,'Daily Order Tracker'!$F$4:$F$93,A10,'Daily Order Tracker'!$Q$4:$Q$93,"<>"),0) -> 6.5714286 | I10: =COUNTIFS('Daily Order Tracker'!$F$4:$F$93,A10,'Daily Order Tracker'!$S$4:$S$93,"Y") -> 6 | J10: =INDEX(Hourly_Helper!$Z$2:$Z$11,MATCH(A10,Hourly_Helper!$A$2:$A$11,0)) -> 2 | K10: =IFERROR((E10-I10)/E10,0) -> 0.33333333
A11: Swish Kitchen - BTM Layout | B11: BTM Layout | C11: Night (6PM-2AM) | D11: Meera Pillai | E11: =COUNTIF('Daily Order Tracker'!$F$4:$F$93,A11) -> 9 | F11: =COUNTIFS('Daily Order Tracker'!$F$4:$F$93,A11,'Daily Order Tracker'!$N$4:$N$93,"Preparing") -> 1 | G11: =COUNTIFS('Daily Order Tracker'!$F$4:$F$93,A11,'Daily Order Tracker'!$N$4:$N$93,"Ready") -> 0 | H11: =IFERROR(AVERAGEIFS('Daily Order Tracker'!$Q$4:$Q$93,'Daily Order Tracker'!$F$4:$F$93,A11,'Daily Order Tracker'!$Q$4:$Q$93,"<>"),0) -> 5.875 | I11: =COUNTIFS('Daily Order Tracker'!$F$4:$F$93,A11,'Daily Order Tracker'!$S$4:$S$93,"Y") -> 6 | J11: =INDEX(Hourly_Helper!$Z$2:$Z$11,MATCH(A11,Hourly_Helper!$A$2:$A$11,0)) -> 2 | K11: =IFERROR((E11-I11)/E11,0) -> 0.33333333
A12: Swish Kitchen - Bellandur | B12: Bellandur | C12: Morning (7AM-3PM) | D12: Naveen Gowda | E12: =COUNTIF('Daily Order Tracker'!$F$4:$F$93,A12) -> 9 | F12: =COUNTIFS('Daily Order Tracker'!$F$4:$F$93,A12,'Daily Order Tracker'!$N$4:$N$93,"Preparing") -> 0 | G12: =COUNTIFS('Daily Order Tracker'!$F$4:$F$93,A12,'Daily Order Tracker'!$N$4:$N$93,"Ready") -> 0 | H12: =IFERROR(AVERAGEIFS('Daily Order Tracker'!$Q$4:$Q$93,'Daily Order Tracker'!$F$4:$F$93,A12,'Daily Order Tracker'!$Q$4:$Q$93,"<>"),0) -> 6 | I12: =COUNTIFS('Daily Order Tracker'!$F$4:$F$93,A12,'Daily Order Tracker'!$S$4:$S$93,"Y") -> 6 | J12: =INDEX(Hourly_Helper!$Z$2:$Z$11,MATCH(A12,Hourly_Helper!$A$2:$A$11,0)) -> 2 | K12: =IFERROR((E12-I12)/E12,0) -> 0.33333333
A13: Swish Kitchen - Sarjapur | B13: Sarjapur | C13: Afternoon (11AM-7PM) | D13: Priya Menon | E13: =COUNTIF('Daily Order Tracker'!$F$4:$F$93,A13) -> 9 | F13: =COUNTIFS('Daily Order Tracker'!$F$4:$F$93,A13,'Daily Order Tracker'!$N$4:$N$93,"Preparing") -> 0 | G13: =COUNTIFS('Daily Order Tracker'!$F$4:$F$93,A13,'Daily Order Tracker'!$N$4:$N$93,"Ready") -> 0 | H13: =IFERROR(AVERAGEIFS('Daily Order Tracker'!$Q$4:$Q$93,'Daily Order Tracker'!$F$4:$F$93,A13,'Daily Order Tracker'!$Q$4:$Q$93,"<>"),0) -> 5.5714286 | I13: =COUNTIFS('Daily Order Tracker'!$F$4:$F$93,A13,'Daily Order Tracker'!$S$4:$S$93,"Y") -> 5 | J13: =INDEX(Hourly_Helper!$Z$2:$Z$11,MATCH(A13,Hourly_Helper!$A$2:$A$11,0)) -> 2 | K13: =IFERROR((E13-I13)/E13,0) -> 0.44444444

Sheet Food Preparation Monitor
A1: FOOD PREPARATION MONITOR
A2: Sample batch snapshot — Prep Time and Delay Flag are live formulas.
A3: Item Name | B3: Category | C3: Order Quantity | D3: Prep Start | E3: Prep End | F3: Prep Time (min) | G3: Target Time (min) | H3: Delay Flag
A4: Veg Fried Rice | B4: Rice Bowls | C4: 58 | D4: 0.81805556 | E4: 0.82361111 | F4: =(E4-D4)*1440 -> 8 | G4: 6 | H4: =IF(F4>G4,"DELAYED","On Time") -> DELAYED
A5: Chicken Noodles | B5: Noodles | C5: 23 | D5: 0.5875 | E5: 0.59652778 | F5: =(E5-D5)*1440 -> 13 | G5: 10 | H5: =IF(F5>G5,"DELAYED","On Time") -> DELAYED
A6: Paneer Wrap | B6: Snacks | C6: 51 | D6: 0.57361111 | E6: 0.58611111 | F6: =(E6-D6)*1440 -> 18 | G6: 12 | H6: =IF(F6>G6,"DELAYED","On Time") -> DELAYED
A7: Cold Coffee | B7: Beverages | C7: 34 | D7: 0.58680556 | E7: 0.59305556 | F7: =(E7-D7)*1440 -> 9 | G7: 10 | H7: =IF(F7>G7,"DELAYED","On Time") -> On Time
A8: Gulab Jamun | B8: Sweets | C8: 59 | D8: 0.57013889 | E8: 0.58055556 | F8: =(E8-D8)*1440 -> 15 | G8: 12 | H8: =IF(F8>G8,"DELAYED","On Time") -> DELAYED
A9: Masala Dosa Roll | B9: Wraps | C9: 31 | D9: 0.78125 | E9: 0.78611111 | F9: =(E9-D9)*1440 -> 7 | G9: 6 | H9: =IF(F9>G9,"DELAYED","On Time") -> DELAYED
A10: Chicken Momos | B10: Rice Bowls | C10: 63 | D10: 0.82638889 | E10: 0.83125 | F10: =(E10-D10)*1440 -> 7 | G10: 8 | H10: =IF(F10>G10,"DELAYED","On Time") -> On Time
A11: Veg Momos | B11: Noodles | C11: 26 | D11: 0.82083333 | E11: 0.83055556 | F11: =(E11-D11)*1440 -> 14 | G11: 9 | H11: =IF(F11>G11,"DELAYED","On Time") -> DELAYED
A12: Mango Lassi | B12: Snacks | C12: 61 | D12: 0.39097222 | E12: 0.39583333 | F12: =(E12-D12)*1440 -> 7 | G12: 8 | H12: =IF(F12>G12,"DELAYED","On Time") -> On Time
A13: Butter Naan Wrap | B13: Beverages | C13: 42 | D13: 0.61736111 | E13: 0.62361111 | F13: =(E13-D13)*1440 -> 9 | G13: 9 | H13: =IF(F13>G13,"DELAYED","On Time") -> On Time
A14: Egg Fried Rice | B14: Sweets | C14: 43 | D14: 0.46458333 | E14: 0.46944444 | F14: =(E14-D14)*1440 -> 7 | G14: 6 | H14: =IF(F14>G14,"DELAYED","On Time") -> DELAYED
A15: Chocolate Shake | B15: Wraps | C15: 27 | D15: 0.74236111 | E15: 0.75277778 | F15: =(E15-D15)*1440 -> 15 | G15: 10 | H15: =IF(F15>G15,"DELAYED","On Time") -> DELAYED
... A23: Schezwan Noodles | B23: Noodles | C23: 51 | D23: 0.64722222 | E23: 0.65625 | F23: =(E23-D23)*1440 -> 13 | G23: 10 | H23: =IF(F23>G23,"DELAYED","On Time") -> DELAYED

Sheet Rider Performance Tracker
A1: RIDER PERFORMANCE TRACKER
A2: Assumptions box (right) drives Earnings — edit the blue input cell to re-price all riders.
A3: Rider ID | B3: Rider Name | C3: Zone | D3: Shift | E3: Orders Assigned | F3: Orders Delivered | G3: Average Delivery Time (min) | H3: Distance Covered (km) | I3: Online Hours | J3: Idle Time (hrs) | K3: Earnings (₹) | L3: Incentives (₹) | M3: Acceptance Rate | O3: ASSUMPTIONS
A4: R001 | B4: Rahul Verma | C4: Koramangala | D4: Morning (7AM-3PM) | E4: =COUNTIF('Daily Order Tracker'!$G$4:$G$93,A4) -> 6 | F4: =COUNTIFS('Daily Order Tracker'!$G$4:$G$93,A4,'Daily Order Tracker'!$N$4:$N$93,"Delivered") -> 5 | G4: =IFERROR(AVERAGEIFS('Daily Order Tracker'!$M$4:$M$93,'Daily Order Tracker'!$G$4:$G$93,A4,'Daily Order Tracker'!$M$4:$M$93,"<>"),0) -> 8 | H4: 53.8 | I4: 8.3 | J4: =ROUND(MAX(I4-((G4*F4)/60),0),1) -> 7.6 | K4: =F4*$P4+L4 -> 175 | L4: =IF(F4>=15,300,IF(F4>=10,150,0)) -> 0 | M4: =IFERROR(F4/E4,0) -> 0.83333333 | O4: Base Rate / Delivery (₹) | P4: 35
A5: R002 | B5: Sandeep Yadav | C5: Koramangala | D5: Afternoon (11AM-7PM) | E5: =COUNTIF('Daily Order Tracker'!$G$4:$G$93,A5) -> 3 | F5: =COUNTIFS('Daily Order Tracker'!$G$4:$G$93,A5,'Daily Order Tracker'!$N$4:$N$93,"Delivered") -> 3 | G5: =IFERROR(AVERAGEIFS('Daily Order Tracker'!$M$4:$M$93,'Daily Order Tracker'!$G$4:$G$93,A5,'Daily Order Tracker'!$M$4:$M$93,"<>"),0) -> 15.333333 | H5: 47.6 | I5: 5.6 | J5: =ROUND(MAX(I5-((G5*F5)/60),0),1) -> 4.8 | K5: =F5*$P4+L5 -> 105 | L5: =IF(F5>=15,300,IF(F5>=10,150,0)) -> 0 | M5: =IFERROR(F5/E5,0) -> 1 | O5: Assumed Max Orders/Day | P5: 20
A6: R003 | B6: Kiran Kumar | C6: HSR Layout | D6: Evening (3PM-11PM) | E6: =COUNTIF('Daily Order Tracker'!$G$4:$G$93,A6) -> 3 | F6: =COUNTIFS('Daily Order Tracker'!$G$4:$G$93,A6,'Daily Order Tracker'!$N$4:$N$93,"Delivered") -> 2 | G6: =IFERROR(AVERAGEIFS('Daily Order Tracker'!$M$4:$M$93,'Daily Order Tracker'!$G$4:$G$93,A6,'Daily Order Tracker'!$M$4:$M$93,"<>"),0) -> 13 | H6: 27.3 | I6: 7.6 | J6: =ROUND(MAX(I6-((G6*F6)/60),0),1) -> 7.2 | K6: =F6*$P4+L6 -> 70 | L6: =IF(F6>=15,300,IF(F6>=10,150,0)) -> 0 | M6: =IFERROR(F6/E6,0) -> 0.66666667
A7: R004 | B7: Manoj Das | C7: HSR Layout | D7: Night (6PM-2AM) | E7: =COUNTIF('Daily Order Tracker'!$G$4:$G$93,A7) -> 6 | F7: =COUNTIFS('Daily Order Tracker'!$G$4:$G$93,A7,'Daily Order Tracker'!$N$4:$N$93,"Delivered") -> 5 | G7: =IFERROR(AVERAGEIFS('Daily Order Tracker'!$M$4:$M$93,'Daily Order Tracker'!$G$4:$G$93,A7,'Daily Order Tracker'!$M$4:$M$93,"<>"),0) -> 11.4 | H7: 50.3 | I7: 7.2 | J7: =ROUND(MAX(I7-((G7*F7)/60),0),1) -> 6.2 | K7: =F7*$P4+L7 -> 175 | L7: =IF(F7>=15,300,IF(F7>=10,150,0)) -> 0 | M7: =IFERROR(F7/E7,0) -> 0.83333333
A8: R005 | B8: Vishal Chauhan | C8: Indiranagar | D8: Morning (7AM-3PM) | E8: =COUNTIF('Daily Order Tracker'!$G$4:$G$93,A8) -> 6 | F8: =COUNTIFS('Daily Order Tracker'!$G$4:$G$93,A8,'Daily Order Tracker'!$N$4:$N$93,"Delivered") -> 4 | G8: =IFERROR(AVERAGEIFS('Daily Order Tracker'!$M$4:$M$93,'Daily Order Tracker'!$G$4:$G$93,A8,'Daily Order Tracker'!$M$4:$M$93,"<>"),0) -> 11.75 | H8: 21.8 | I8: 8.4 | J8: =ROUND(MAX(I8-((G8*F8)/60),0),1) -> 7.6 | K8: =F8*$P4+L8 -> 140 | L8: =IF(F8>=15,300,IF(F8>=10,150,0)) -> 0 | M8: =IFERROR(F8/E8,0) -> 0.66666667
A9: R006 | B9: Ajay Patil | C9: Indiranagar | D9: Afternoon (11AM-7PM) | E9: =COUNTIF('Daily Order Tracker'!$G$4:$G$93,A9) -> 3 | F9: =COUNTIFS('Daily Order Tracker'!$G$4:$G$93,A9,'Daily Order Tracker'!$N$4:$N$93,"Delivered") -> 3 | G9: =IFERROR(AVERAGEIFS('Daily Order Tracker'!$M$4:$M$93,'Daily Order Tracker'!$G$4:$G$93,A9,'Daily Order Tracker'!$M$4:$M$93,"<>"),0) -> 13 | H9: 49.5 | I9: 6.1 | J9: =ROUND(MAX(I9-((G9*F9)/60),0),1) -> 5.5 | K9: =F9*$P4+L9 -> 105 | L9: =IF(F9>=15,300,IF(F9>=10,150,0)) -> 0 | M9: =IFERROR(F9/E9,0) -> 1
A10: R007 | B10: Suraj Shetty | C10: Whitefield | D10: Evening (3PM-11PM) | E10: =COUNTIF('Daily Order Tracker'!$G$4:$G$93,A10) -> 3 | F10: =COUNTIFS('Daily Order Tracker'!$G$4:$G$93,A10,'Daily Order Tracker'!$N$4:$N$93,"Delivered") -> 3 | G10: =IFERROR(AVERAGEIFS('Daily Order Tracker'!$M$4:$M$93,'Daily Order Tracker'!$G$4:$G$93,A10,'Daily Order Tracker'!$M$4:$M$93,"<>"),0) -> 11.666667 | H10: 46.2 | I10: 6.1 | J10: =ROUND(MAX(I10-((G10*F10)/60),0),1) -> 5.5 | K10: =F10*$P4+L10 -> 105 | L10: =IF(F10>=15,300,IF(F10>=10,150,0)) -> 0 | M10: =IFERROR(F10/E10,0) -> 1
A11: R008 | B11: Rohit Bose | C11: Whitefield | D11: Night (6PM-2AM) | E11: =COUNTIF('Daily Order Tracker'!$G$4:$G$93,A11) -> 6 | F11: =COUNTIFS('Daily Order Tracker'!$G$4:$G$93,A11,'Daily Order Tracker'!$N$4:$N$93,"Delivered") -> 4 | G11: =IFERROR(AVERAGEIFS('Daily Order Tracker'!$M$4:$M$93,'Daily Order Tracker'!$G$4:$G$93,A11,'Daily Order Tracker'!$M$4:$M$93,"<>"),0) -> 12 | H11: 51.5 | I11: 5.6 | J11: =ROUND(MAX(I11-((G11*F11)/60),0),1) -> 4.8 | K11: =F11*$P4+L11 -> 140 | L11: =IF(F11>=15,300,IF(F11>=10,150,0)) -> 0 | M11: =IFERROR(F11/E11,0) -> 0.66666667
A12: R009 | B12: Farhan Ali | C12: Electronic City | D12: Morning (7AM-3PM) | E12: =COUNTIF('Daily Order Tracker'!$G$4:$G$93,A12) -> 6 | F12: =COUNTIFS('Daily Order Tracker'!$G$4:$G$93,A12,'Daily Order Tracker'!$N$4:$N$93,"Delivered") -> 5 | G12: =IFERROR(AVERAGEIFS('Daily Order Tracker'!$M$4:$M$93,'Daily Order Tracker'!$G$4:$G$93,A12,'Daily Order Tracker'!$M$4:$M$93,"<>"),0) -> 12.2 | H12: 34.2 | I12: 8.8 | J12: =ROUND(MAX(I12-((G12*F12)/60),0),1) -> 7.8 | K12: =F12*$P4+L12 -> 175 | L12: =IF(F12>=15,300,IF(F12>=10,150,0)) -> 0 | M12: =IFERROR(F12/E12,0) -> 0.83333333
A13: R010 | B13: Gautam Joshi | C13: Electronic City | D13: Afternoon (11AM-7PM) | E13: =COUNTIF('Daily Order Tracker'!$G$4:$G$93,A13) -> 3 | F13: =COUNTIFS('Daily Order Tracker'!$G$4:$G$93,A13,'Daily Order Tracker'!$N$4:$N$93,"Delivered") -> 3 | G13: =IFERROR(AVERAGEIFS('Daily Order Tracker'!$M$4:$M$93,'Daily Order Tracker'!$G$4:$G$93,A13,'Daily Order Tracker'!$M$4:$M$93,"<>"),0) -> 14.333333 | H13: 26.2 | I13: 6.8 | J13: =ROUND(MAX(I13-((G13*F13)/60),0),1) -> 6.1 | K13: =F13*$P4+L13 -> 105 | L13: =IF(F13>=15,300,IF(F13>=10,150,0)) -> 0 | M13: =IFERROR(F13/E13,0) -> 1
A14: R011 | B14: Nikhil Rane | C14: Marathahalli | D14: Evening (3PM-11PM) | E14: =COUNTIF('Daily Order Tracker'!$G$4:$G$93,A14) -> 3 | F14: =COUNTIFS('Daily Order Tracker'!$G$4:$G$93,A14,'Daily Order Tracker'!$N$4:$N$93,"Delivered") -> 2 | G14: =IFERROR(AVERAGEIFS('Daily Order Tracker'!$M$4:$M$93,'Daily Order Tracker'!$G$4:$G$93,A14,'Daily Order Tracker'!$M$4:$M$93,"<>"),0) -> 11 | H14: 30.9 | I14: 5.1 | J14: =ROUND(MAX(I14-((G14*F14)/60),0),1) -> 4.7 | K14: =F14*$P4+L14 -> 70 | L14: =IF(F14>=15,300,IF(F14>=10,150,0)) -> 0 | M14: =IFERROR(F14/E14,0) -> 0.66666667
A15: R012 | B15: Prakash Naidu | C15: Marathahalli | D15: Night (6PM-2AM) | E15: =COUNTIF('Daily Order Tracker'!$G$4:$G$93,A15) -> 6 | F15: =COUNTIFS('Daily Order Tracker'!$G$4:$G$93,A15,'Daily Order Tracker'!$N$4:$N$93,"Delivered") -> 3 | G15: =IFERROR(AVERAGEIFS('Daily Order Tracker'!$M$4:$M$93,'Daily Order Tracker'!$G$4:$G$93,A15,'Daily Order Tracker'!$M$4:$M$93,"<>"),0) -> 10.333333 | H15: 20 | I15: 7 | J15: =ROUND(MAX(I15-((G15*F15)/60),0),1) -> 6.5 | K15: =F15*$P4+L15 -> 105 | L15: =IF(F15>=15,300,IF(F15>=10,150,0)) -> 0 | M15: =IFERROR(F15/E15,0) -> 0.5
A16: R013 | B16: Irfan Khan | C16: JP Nagar | D16: Morning (7AM-3PM) | E16: =COUNTIF('Daily Order Tracker'!$G$4:$G$93,A16) -> 6 | F16: =COUNTIFS('Daily Order Tracker'!$G$4:$G$93,A16,'Daily Order Tracker'!$N$4:$N$93,"Delivered") -> 4 | G16: =IFERROR(AVERAGEIFS('Daily Order Tracker'!$M$4:$M$93,'Daily Order Tracker'!$G$4:$G$93,A16,'Daily Order Tracker'!$M$4:$M$93,"<>"),0) -> 13.25 | H16: 26.7 | I16: 9 | J16: =ROUND(MAX(I16-((G16*F16)/60),0),1) -> 8.1 | K16: =F16*$P4+L16 -> 140 | L16: =IF(F16>=15,300,IF(F16>=10,150,0)) -> 0 | M16: =IFERROR(F16/E16,0) -> 0.66666667
A17: R014 | B17: Tarun Bhatia | C17: JP Nagar | D17: Afternoon (11AM-7PM) | E17: =COUNTIF('Daily Order Tracker'!$G$4:$G$93,A17) -> 3 | F17: =COUNTIFS('Daily Order Tracker'!$G$4:$G$93,A17,'Daily Order Tracker'!$N$4:$N$93,"Delivered") -> 3 | G17: =IFERROR(AVERAGEIFS('Daily Order Tracker'!$M$4:$M$93,'Daily Order Tracker'!$G$4:$G$93,A17,'Daily Order Tracker'!$M$4:$M$93,"<>"),0) -> 10.666667 | H17: 31.9 | I17: 5.1 | J17: =ROUND(MAX(I17-((G17*F17)/60),0),1) -> 4.6 | K17: =F17*$P4+L17 -> 105 | L17: =IF(F17>=15,300,IF(F17>=10,150,0)) -> 0 | M17: =IFERROR(F17/E17,0) -> 1
A18: R015 | B18: Yusuf Sheikh | C18: BTM Layout | D18: Evening (3PM-11PM) | E18: =COUNTIF('Daily Order Tracker'!$G$4:$G$93,A18) -> 3 | F18: =COUNTIFS('Daily Order Tracker'!$G$4:$G$93,A18,'Daily Order Tracker'!$N$4:$N$93,"Delivered") -> 3 | G18: =IFERROR(AVERAGEIFS('Daily Order Tracker'!$M$4:$M$93,'Daily Order Tracker'!$G$4:$G$93,A18,'Daily Order Tracker'!$M$4:$M$93,"<>"),0) -> 14.333333 | H18: 52.4 | I18: 8.4 | J18: =ROUND(MAX(I18-((G18*F18)/60),0),1) -> 7.7 | K18: =F18*$P4+L18 -> 105 | L18: =IF(F18>=15,300,IF(F18>=10,150,0)) -> 0 | M18: =IFERROR(F18/E18,0) -> 1
A19: R016 | B19: Aditya Menon | C19: BTM Layout | D19: Night (6PM-2AM) | E19: =COUNTIF('Daily Order Tracker'!$G$4:$G$93,A19) -> 6 | F19: =COUNTIFS('Daily Order Tracker'!$G$4:$G$93,A19,'Daily Order Tracker'!$N$4:$N$93,"Delivered") -> 5 | G19: =IFERROR(AVERAGEIFS('Daily Order Tracker'!$M$4:$M$93,'Daily Order Tracker'!$G$4:$G$93,A19,'Daily Order Tracker'!$M$4:$M$93,"<>"),0) -> 12.2 | H19: 42 | I19: 8.2 | J19: =ROUND(MAX(I19-((G19*F19)/60),0),1) -> 7.2 | K19: =F19*$P4+L19 -> 175 | L19: =IF(F19>=15,300,IF(F19>=10,150,0)) -> 0 | M19: =IFERROR(F19/E19,0) -> 0.83333333
A20: R017 | B20: Sameer Qureshi | C20: Bellandur | D20: Morning (7AM-3PM) | E20: =COUNTIF('Daily Order Tracker'!$G$4:$G$93,A20) -> 6 | F20: =COUNTIFS('Daily Order Tracker'!$G$4:$G$93,A20,'Daily Order Tracker'!$N$4:$N$93,"Delivered") -> 5 | G20: =IFERROR(AVERAGEIFS('Daily Order Tracker'!$M$4:$M$93,'Daily Order Tracker'!$G$4:$G$93,A20,'Daily Order Tracker'!$M$4:$M$93,"<>"),0) -> 10 | H20: 23.1 | I20: 6.1 | J20: =ROUND(MAX(I20-((G20*F20)/60),0),1) -> 5.3 | K20: =F20*$P4+L20 -> 175 | L20: =IF(F20>=15,300,IF(F20>=10,150,0)) -> 0 | M20: =IFERROR(F20/E20,0) -> 0.83333333
A21: R018 | B21: Bala Murugan | C21: Bellandur | D21: Afternoon (11AM-7PM) | E21: =COUNTIF('Daily Order Tracker'!$G$4:$G$93,A21) -> 3 | F21: =COUNTIFS('Daily Order Tracker'!$G$4:$G$93,A21,'Daily Order Tracker'!$N$4:$N$93,"Delivered") -> 3 | G21: =IFERROR(AVERAGEIFS('Daily Order Tracker'!$M$4:$M$93,'Daily Order Tracker'!$G$4:$G$93,A21,'Daily Order Tracker'!$M$4:$M$93,"<>"),0) -> 13 | H21: 48.7 | I21: 7.8 | J21: =ROUND(MAX(I21-((G21*F21)/60),0),1) -> 7.2 | K21: =F21*$P4+L21 -> 105 | L21: =IF(F21>=15,300,IF(F21>=10,150,0)) -> 0 | M21: =IFERROR(F21/E21,0) -> 1
A22: R019 | B22: Harish Chandra | C22: Sarjapur | D22: Evening (3PM-11PM) | E22: =COUNTIF('Daily Order Tracker'!$G$4:$G$93,A22) -> 3 | F22: =COUNTIFS('Daily Order Tracker'!$G$4:$G$93,A22,'Daily Order Tracker'!$N$4:$N$93,"Delivered") -> 2 | G22: =IFERROR(AVERAGEIFS('Daily Order Tracker'!$M$4:$M$93,'Daily Order Tracker'!$G$4:$G$93,A22,'Daily Order Tracker'!$M$4:$M$93,"<>"),0) -> 10 | H22: 23.1 | I22: 7.8 | J22: =ROUND(MAX(I22-((G22*F22)/60),0),1) -> 7.5 | K22: =F22*$P4+L22 -> 70 | L22: =IF(F22>=15,300,IF(F22>=10,150,0)) -> 0 | M22: =IFERROR(F22/E22,0) -> 0.66666667
A23: R020 | B23: Dinesh Kumar | C23: Sarjapur | D23: Night (6PM-2AM) | E23: =COUNTIF('Daily Order Tracker'!$G$4:$G$93,A23) -> 6 | F23: =COUNTIFS('Daily Order Tracker'!$G$4:$G$93,A23,'Daily Order Tracker'!$N$4:$N$93,"Delivered") -> 5 | G23: =IFERROR(AVERAGEIFS('Daily Order Tracker'!$M$4:$M$93,'Daily Order Tracker'!$G$4:$G$93,A23,'Daily Order Tracker'!$M$4:$M$93,"<>"),0) -> 12.4 | H23: 34.6 | I23: 5 | J23: =ROUND(MAX(I23-((G23*F23)/60),0),1) -> 4 | K23: =F23*$P4+L23 -> 175 | L23: =IF(F23>=15,300,IF(F23>=10,150,0)) -> 0 | M23: =IFERROR(F23/E23,0) -> 0.83333333

Sheet Zone Performance
A1: ZONE PERFORMANCE — BANGALORE
A2: Auto-aggregated across all 10 Bangalore delivery zones.
A3: Zone | B3: Orders | C3: Revenue (₹) | D3: Avg Delivery Time (min) | E3: Avg Prep Time (min) | F3: Active Riders | G3: Active Kitchens | H3: Cancellation Rate | I3: Customer Rating
A4: Koramangala | B4: =COUNTIF('Daily Order Tracker'!$E$4:$E$93,A4) -> 9 | C4: =SUMIFS('Daily Order Tracker'!$P$4:$P$93,'Daily Order Tracker'!$E$4:$E$93,A4,'Daily Order Tracker'!$N$4:$N$93,"Delivered") -> 3300 | D4: =IFERROR(AVERAGEIFS('Daily Order Tracker'!$M$4:$M$93,'Daily Order Tracker'!$E$4:$E$93,A4,'Daily Order Tracker'!$M$4:$M$93,"<>"),0) -> 10.75 | E4: =IFERROR(AVERAGEIFS('Daily Order Tracker'!$Q$4:$Q$93,'Daily Order Tracker'!$E$4:$E$93,A4,'Daily Order Tracker'!$Q$4:$Q$93,"<>"),0) -> 4.875 | F4: =COUNTIF('Rider Performance Tracker'!$C$4:$C$23,A4) -> 2 | G4: =COUNTIF('Kitchen Operations Tracker'!$B$4:$B$13,A4) -> 1 | H4: =IFERROR(COUNTIFS('Daily Order Tracker'!$E$4:$E$93,A4,'Daily Order Tracker'!$N$4:$N$93,"Cancelled")/B4,0) -> 0 | I4: 4
A5: HSR Layout | B5: =COUNTIF('Daily Order Tracker'!$E$4:$E$93,A5) -> 9 | C5: =SUMIFS('Daily Order Tracker'!$P$4:$P$93,'Daily Order Tracker'!$E$4:$E$93,A5,'Daily Order Tracker'!$N$4:$N$93,"Delivered") -> 3262 | D5: =IFERROR(AVERAGEIFS('Daily Order Tracker'!$M$4:$M$93,'Daily Order Tracker'!$E$4:$E$93,A5,'Daily Order Tracker'!$M$4:$M$93,"<>"),0) -> 11.857143 | E5: =IFERROR(AVERAGEIFS('Daily Order Tracker'!$Q$4:$Q$93,'Daily Order Tracker'!$E$4:$E$93,A5,'Daily Order Tracker'!$Q$4:$Q$93,"<>"),0) -> 6.5 | F5: =COUNTIF('Rider Performance Tracker'!$C$4:$C$23,A5) -> 2 | G5: =COUNTIF('Kitchen Operations Tracker'!$B$4:$B$13,A5) -> 1 | H5: =IFERROR(COUNTIFS('Daily Order Tracker'!$E$4:$E$93,A5,'Daily Order Tracker'!$N$4:$N$93,"Cancelled")/B5,0) -> 0.11111111 | I5: 4.2
A6: Indiranagar | B6: =COUNTIF('Daily Order Tracker'!$E$4:$E$93,A6) -> 9 | C6: =SUMIFS('Daily Order Tracker'!$P$4:$P$93,'Daily Order Tracker'!$E$4:$E$93,A6,'Daily Order Tracker'!$N$4:$N$93,"Delivered") -> 3017 | D6: =IFERROR(AVERAGEIFS('Daily Order Tracker'!$M$4:$M$93,'Daily Order Tracker'!$E$4:$E$93,A6,'Daily Order Tracker'!$M$4:$M$93,"<>"),0) -> 12.285714 | E6: =IFERROR(AVERAGEIFS('Daily Order Tracker'!$Q$4:$Q$93,'Daily Order Tracker'!$E$4:$E$93,A6,'Daily Order Tracker'!$Q$4:$Q$93,"<>"),0) -> 5.7142857 | F6: =COUNTIF('Rider Performance Tracker'!$C$4:$C$23,A6) -> 2 | G6: =COUNTIF('Kitchen Operations Tracker'!$B$4:$B$13,A6) -> 1 | H6: =IFERROR(COUNTIFS('Daily Order Tracker'!$E$4:$E$93,A6,'Daily Order Tracker'!$N$4:$N$93,"Cancelled")/B6,0) -> 0.22222222 | I6: 4.7
A7: Whitefield | B7: =COUNTIF('Daily Order Tracker'!$E$4:$E$93,A7) -> 9 | C7: =SUMIFS('Daily Order Tracker'!$P$4:$P$93,'Daily Order Tracker'!$E$4:$E$93,A7,'Daily Order Tracker'!$N$4:$N$93,"Delivered") -> 2851 | D7: =IFERROR(AVERAGEIFS('Daily Order Tracker'!$M$4:$M$93,'Daily Order Tracker'!$E$4:$E$93,A7,'Daily Order Tracker'!$M$4:$M$93,"<>"),0) -> 11.857143 | E7: =IFERROR(AVERAGEIFS('Daily Order Tracker'!$Q$4:$Q$93,'Daily Order Tracker'!$E$4:$E$93,A7,'Daily Order Tracker'!$Q$4:$Q$93,"<>"),0) -> 6.2857143 | F7: =COUNTIF('Rider Performance Tracker'!$C$4:$C$23,A7) -> 2 | G7: =COUNTIF('Kitchen Operations Tracker'!$B$4:$B$13,A7) -> 1 | H7: =IFERROR(COUNTIFS('Daily Order Tracker'!$E$4:$E$93,A7,'Daily Order Tracker'!$N$4:$N$93,"Cancelled")/B7,0) -> 0.22222222 | I7: 4.4
A8: Electronic City | B8: =COUNTIF('Daily Order Tracker'!$E$4:$E$93,A8) -> 9 | C8: =SUMIFS('Daily Order Tracker'!$P$4:$P$93,'Daily Order Tracker'!$E$4:$E$93,A8,'Daily Order Tracker'!$N$4:$N$93,"Delivered") -> 3082 | D8: =IFERROR(AVERAGEIFS('Daily Order Tracker'!$M$4:$M$93,'Daily Order Tracker'!$E$4:$E$93,A8,'Daily Order Tracker'!$M$4:$M$93,"<>"),0) -> 13 | E8: =IFERROR(AVERAGEIFS('Daily Order Tracker'!$Q$4:$Q$93,'Daily Order Tracker'!$E$4:$E$93,A8,'Daily Order Tracker'!$Q$4:$Q$93,"<>"),0) -> 6.75 | F8: =COUNTIF('Rider Performance Tracker'!$C$4:$C$23,A8) -> 2 | G8: =COUNTIF('Kitchen Operations Tracker'!$B$4:$B$13,A8) -> 1 | H8: =IFERROR(COUNTIFS('Daily Order Tracker'!$E$4:$E$93,A8,'Daily Order Tracker'!$N$4:$N$93,"Cancelled")/B8,0) -> 0 | I8: 4.6
A9: Marathahalli | B9: =COUNTIF('Daily Order Tracker'!$E$4:$E$93,A9) -> 9 | C9: =SUMIFS('Daily Order Tracker'!$P$4:$P$93,'Daily Order Tracker'!$E$4:$E$93,A9,'Daily Order Tracker'!$N$4:$N$93,"Delivered") -> 2095 | D9: =IFERROR(AVERAGEIFS('Daily Order Tracker'!$M$4:$M$93,'Daily Order Tracker'!$E$4:$E$93,A9,'Daily Order Tracker'!$M$4:$M$93,"<>"),0) -> 10.6 | E9: =IFERROR(AVERAGEIFS('Daily Order Tracker'!$Q$4:$Q$93,'Daily Order Tracker'!$E$4:$E$93,A9,'Daily Order Tracker'!$Q$4:$Q$93,"<>"),0) -> 5.3333333 | F9: =COUNTIF('Rider Performance Tracker'!$C$4:$C$23,A9) -> 2 | G9: =COUNTIF('Kitchen Operations Tracker'!$B$4:$B$13,A9) -> 1 | H9: =IFERROR(COUNTIFS('Daily Order Tracker'!$E$4:$E$93,A9,'Daily Order Tracker'!$N$4:$N$93,"Cancelled")/B9,0) -> 0.33333333 | I9: 4.4
A10: JP Nagar | B10: =COUNTIF('Daily Order Tracker'!$E$4:$E$93,A10) -> 9 | C10: =SUMIFS('Daily Order Tracker'!$P$4:$P$93,'Daily Order Tracker'!$E$4:$E$93,A10,'Daily Order Tracker'!$N$4:$N$93,"Delivered") -> 2651 | D10: =IFERROR(AVERAGEIFS('Daily Order Tracker'!$M$4:$M$93,'Daily Order Tracker'!$E$4:$E$93,A10,'Daily Order Tracker'!$M$4:$M$93,"<>"),0) -> 12.142857 | E10: =IFERROR(AVERAGEIFS('Daily Order Tracker'!$Q$4:$Q$93,'Daily Order Tracker'!$E$4:$E$93,A10,'Daily Order Tracker'!$Q$4:$Q$93,"<>"),0) -> 6.5714286 | F10: =COUNTIF('Rider Performance Tracker'!$C$4:$C$23,A10) -> 2 | G10: =COUNTIF('Kitchen Operations Tracker'!$B$4:$B$13,A10) -> 1 | H10: =IFERROR(COUNTIFS('Daily Order Tracker'!$E$4:$E$93,A10,'Daily Order Tracker'!$N$4:$N$93,"Cancelled")/B10,0) -> 0.11111111 | I10: 4
A11: BTM Layout | B11: =COUNTIF('Daily Order Tracker'!$E$4:$E$93,A11) -> 9 | C11: =SUMIFS('Daily Order Tracker'!$P$4:$P$93,'Daily Order Tracker'!$E$4:$E$93,A11,'Daily Order Tracker'!$N$4:$N$93,"Delivered") -> 3148 | D11: =IFERROR(AVERAGEIFS('Daily Order Tracker'!$M$4:$M$93,'Daily Order Tracker'!$E$4:$E$93,A11,'Daily Order Tracker'!$M$4:$M$93,"<>"),0) -> 13 | E11: =IFERROR(AVERAGEIFS('Daily Order Tracker'!$Q$4:$Q$93,'Daily Order Tracker'!$E$4:$E$93,A11,'Daily Order Tracker'!$Q$4:$Q$93,"<>"),0) -> 5.875 | F11: =COUNTIF('Rider Performance Tracker'!$C$4:$C$23,A11) -> 2 | G11: =COUNTIF('Kitchen Operations Tracker'!$B$4:$B$13,A11) -> 1 | H11: =IFERROR(COUNTIFS('Daily Order Tracker'!$E$4:$E$93,A11,'Daily Order Tracker'!$N$4:$N$93,"Cancelled")/B11,0) -> 0 | I11: 4.2
A12: Bellandur | B12: =COUNTIF('Daily Order Tracker'!$E$4:$E$93,A12) -> 9 | C12: =SUMIFS('Daily Order Tracker'!$P$4:$P$93,'Daily Order Tracker'!$E$4:$E$93,A12,'Daily Order Tracker'!$N$4:$N$93,"Delivered") -> 3542 | D12: =IFERROR(AVERAGEIFS('Daily Order Tracker'!$M$4:$M$93,'Daily Order Tracker'!$E$4:$E$93,A12,'Daily Order Tracker'!$M$4:$M$93,"<>"),0) -> 11.125 | E12: =IFERROR(AVERAGEIFS('Daily Order Tracker'!$Q$4:$Q$93,'Daily Order Tracker'!$E$4:$E$93,A12,'Daily Order Tracker'!$Q$4:$Q$93,"<>"),0) -> 6 | F12: =COUNTIF('Rider Performance Tracker'!$C$4:$C$23,A12) -> 2 | G12: =COUNTIF('Kitchen Operations Tracker'!$B$4:$B$13,A12) -> 1 | H12: =IFERROR(COUNTIFS('Daily Order Tracker'!$E$4:$E$93,A12,'Daily Order Tracker'!$N$4:$N$93,"Cancelled")/B12,0) -> 0 | I12: 4.2
A13: Sarjapur | B13: =COUNTIF('Daily Order Tracker'!$E$4:$E$93,A13) -> 9 | C13: =SUMIFS('Daily Order Tracker'!$P$4:$P$93,'Daily Order Tracker'!$E$4:$E$93,A13,'Daily Order Tracker'!$N$4:$N$93,"Delivered") -> 2647 | D13: =IFERROR(AVERAGEIFS('Daily Order Tracker'!$M$4:$M$93,'Daily Order Tracker'!$E$4:$E$93,A13,'Daily Order Tracker'!$M$4:$M$93,"<>"),0) -> 11.714286 | E13: =IFERROR(AVERAGEIFS('Daily Order Tracker'!$Q$4:$Q$93,'Daily Order Tracker'!$E$4:$E$93,A13,'Daily Order Tracker'!$Q$4:$Q$93,"<>"),0) -> 5.5714286 | F13: =COUNTIF('Rider Performance Tracker'!$C$4:$C$23,A13) -> 2 | G13: =COUNTIF('Kitchen Operations Tracker'!$B$4:$B$13,A13) -> 1 | H13: =IFERROR(COUNTIFS('Daily Order Tracker'!$E$4:$E$93,A13,'Daily Order Tracker'!$N$4:$N$93,"Cancelled")/B13,0) -> 0.11111111 | I13: 3.9

Sheet Inventory Tracker
A1: INVENTORY TRACKER
A2: Closing Stock and Restock Alert are live formulas.
A3: Item | B3: Opening Stock | C3: Received | D3: Used | E3: Closing Stock | F3: Minimum Level | G3: Restock Alert
A4: Basmati Rice (kg) | B4: 157 | C4: 99 | D4: 147 | E4: =B4+C4-D4 -> 109 | F4: 24 | G4: =IF(E4<F4,"REORDER NOW","OK") -> OK
A5: Chicken Breast (kg) | B5: 78 | C5: 83 | D5: 182 | E5: =B5+C5-D5 -> -21 | F5: 54 | G5: =IF(E5<F5,"REORDER NOW","OK") -> REORDER NOW
A6: Paneer (kg) | B6: 54 | C6: 100 | D6: 161 | E6: =B6+C6-D6 -> -7 | F6: 56 | G6: =IF(E6<F6,"REORDER NOW","OK") -> REORDER NOW
A7: Noodles Pack | B7: 111 | C7: 38 | D7: 104 | E7: =B7+C7-D7 -> 45 | F7: 47 | G7: =IF(E7<F7,"REORDER NOW","OK") -> REORDER NOW
A8: Milk (ltr) | B8: 50 | C8: 98 | D8: 120 | E8: =B8+C8-D8 -> 28 | F8: 35 | G8: =IF(E8<F8,"REORDER NOW","OK") -> REORDER NOW
A9: Disposable Bowls | B9: 196 | C9: 73 | D9: 77 | E9: =B9+C9-D9 -> 192 | F9: 25 | G9: =IF(E9<F9,"REORDER NOW","OK") -> OK
A10: Delivery Bags | B10: 184 | C10: 66 | D10: 47 | E10: =B10+C10-D10 -> 203 | F10: 53 | G10: =IF(E10<F10,"REORDER NOW","OK") -> OK
A11: Napkins Pack | B11: 189 | C11: 84 | D11: 231 | E11: =B11+C11-D11 -> 42 | F11: 52 | G11: =IF(E11<F11,"REORDER NOW","OK") -> REORDER NOW
A12: Cold Drink Cans | B12: 191 | C12: 22 | D12: 129 | E12: =B12+C12-D12 -> 84 | F12: 50 | G12: =IF(E12<F12,"REORDER NOW","OK") -> OK
A13: Bread Loaf | B13: 61 | C13: 69 | D13: 125 | E13: =B13+C13-D13 -> 5 | F13: 36 | G13: =IF(E13<F13,"REORDER NOW","OK") -> REORDER NOW
A14: Onions (kg) | B14: 241 | C14: 22 | D14: 121 | E14: =B14+C14-D14 -> 142 | F14: 24 | G14: =IF(E14<F14,"REORDER NOW","OK") -> OK
A15: Tomatoes (kg) | B15: 138 | C15: 50 | D15: 217 | E15: =B15+C15-D15 -> -29 | F15: 60 | G15: =IF(E15<F15,"REORDER NOW","OK") -> REORDER NOW
... A23: Spice Mix Pack | B23: 130 | C23: 59 | D23: 161 | E23: =B23+C23-D23 -> 28 | F23: 45 | G23: =IF(E23<F23,"REORDER NOW","OK") -> REORDER NOW

Sheet Rider Attendance
A1: RIDER ATTENDANCE
A2: Rider Name uses VLOOKUP against Rider Performance Tracker.
A3: Date | B3: Rider ID | C3: Rider Name | D3: Check-in | E3: Check-out | F3: Break Time (hrs) | G3: Total Hours | H3: Attendance Status
A4: 46280 | B4: R001 | C4: =IFERROR(VLOOKUP(B4,'Rider Performance Tracker'!$A$4:$B$23,2,FALSE()),"") -> Rahul Verma | F4: 0 | G4: 0 | H4: Leave
A5: 46280 | B5: R002 | C5: =IFERROR(VLOOKUP(B5,'Rider Performance Tracker'!$A$4:$B$23,2,FALSE()),"") -> Sandeep Yadav | D5: 0.33472222 | E5: 0.62638889 | F5: 0.8 | G5: =ROUND(((E5-D5)*24)-F5,1) -> 6.2 | H5: Present
A6: 46280 | B6: R003 | C6: =IFERROR(VLOOKUP(B6,'Rider Performance Tracker'!$A$4:$B$23,2,FALSE()),"") -> Kiran Kumar | D6: 0.37152778 | E6: 0.66319444 | F6: 0.8 | G6: =ROUND(((E6-D6)*24)-F6,1) -> 6.2 | H6: Present
A7: 46280 | B7: R004 | C7: =IFERROR(VLOOKUP(B7,'Rider Performance Tracker'!$A$4:$B$23,2,FALSE()),"") -> Manoj Das | D7: 0.55347222 | E7: 0.72013889 | F7: 0.4 | G7: =ROUND(((E7-D7)*24)-F7,1) -> 3.6 | H7: Half Day
A8: 46280 | B8: R005 | C8: =IFERROR(VLOOKUP(B8,'Rider Performance Tracker'!$A$4:$B$23,2,FALSE()),"") -> Vishal Chauhan | D8: 0.36597222 | E8: 0.65763889 | F8: 0.6 | G8: =ROUND(((E8-D8)*24)-F8,1) -> 6.4 | H8: Present
A9: 46280 | B9: R006 | C9: =IFERROR(VLOOKUP(B9,'Rider Performance Tracker'!$A$4:$B$23,2,FALSE()),"") -> Ajay Patil | F9: 0 | G9: 0 | H9: Leave
A10: 46280 | B10: R007 | C10: =IFERROR(VLOOKUP(B10,'Rider Performance Tracker'!$A$4:$B$23,2,FALSE()),"") -> Suraj Shetty | D10: 0.31319444 | E10: 0.60486111 | F10: 0.8 | G10: =ROUND(((E10-D10)*24)-F10,1) -> 6.2 | H10: Present
A11: 46280 | B11: R008 | C11: =IFERROR(VLOOKUP(B11,'Rider Performance Tracker'!$A$4:$B$23,2,FALSE()),"") -> Rohit Bose | D11: 0.38680556 | E11: 0.67847222 | F11: 0.9 | G11: =ROUND(((E11-D11)*24)-F11,1) -> 6.1 | H11: Present
A12: 46280 | B12: R009 | C12: =IFERROR(VLOOKUP(B12,'Rider Performance Tracker'!$A$4:$B$23,2,FALSE()),"") -> Farhan Ali | D12: 0.31041667 | E12: 0.60208333 | F12: 0.7 | G12: =ROUND(((E12-D12)*24)-F12,1) -> 6.3 | H12: Present
A13: 46280 | B13: R010 | C13: =IFERROR(VLOOKUP(B13,'Rider Performance Tracker'!$A$4:$B$23,2,FALSE()),"") -> Gautam Joshi | D13: 0.59583333 | E13: 0.7625 | F13: 0.5 | G13: =ROUND(((E13-D13)*24)-F13,1) -> 3.5 | H13: Half Day
A14: 46280 | B14: R011 | C14: =IFERROR(VLOOKUP(B14,'Rider Performance Tracker'!$A$4:$B$23,2,FALSE()),"") -> Nikhil Rane | D14: 0.3875 | E14: 0.67916667 | F14: 0.5 | G14: =ROUND(((E14-D14)*24)-F14,1) -> 6.5 | H14: Present
A15: 46280 | B15: R012 | C15: =IFERROR(VLOOKUP(B15,'Rider Performance Tracker'!$A$4:$B$23,2,FALSE()),"") -> Prakash Naidu | D15: 0.34027778 | E15: 0.63194444 | F15: 0.8 | G15: =ROUND(((E15-D15)*24)-F15,1) -> 6.2 | H15: Present
A16: 46280 | B16: R013 | C16: =IFERROR(VLOOKUP(B16,'Rider Performance Tracker'!$A$4:$B$23,2,FALSE()),"") -> Irfan Khan | D16: 0.32361111 | E16: 0.61527778 | F16: 0.9 | G16: =ROUND(((E16-D16)*24)-F16,1) -> 6.1 | H16: Present
A17: 46280 | B17: R014 | C17: =IFERROR(VLOOKUP(B17,'Rider Performance Tracker'!$A$4:$B$23,2,FALSE()),"") -> Tarun Bhatia | D17: 0.34513889 | E17: 0.63680556 | F17: 0.7 | G17: =ROUND(((E17-D17)*24)-F17,1) -> 6.3 | H17: Present
A18: 46280 | B18: R015 | C18: =IFERROR(VLOOKUP(B18,'Rider Performance Tracker'!$A$4:$B$23,2,FALSE()),"") -> Yusuf Sheikh | D18: 0.29444444 | E18: 0.58611111 | F18: 0.8 | G18: =ROUND(((E18-D18)*24)-F18,1) -> 6.2 | H18: Present
A19: 46280 | B19: R016 | C19: =IFERROR(VLOOKUP(B19,'Rider Performance Tracker'!$A$4:$B$23,2,FALSE()),"") -> Aditya Menon | D19: 0.41041667 | E19: 0.70208333 | F19: 0.8 | G19: =ROUND(((E19-D19)*24)-F19,1) -> 6.2 | H19: Present
A20: 46280 | B20: R017 | C20: =IFERROR(VLOOKUP(B20,'Rider Performance Tracker'!$A$4:$B$23,2,FALSE()),"") -> Sameer Qureshi | D20: 0.29791667 | E20: 0.58958333 | F20: 0.9 | G20: =ROUND(((E20-D20)*24)-F20,1) -> 6.1 | H20: Present
A21: 46280 | B21: R018 | C21: =IFERROR(VLOOKUP(B21,'Rider Performance Tracker'!$A$4:$B$23,2,FALSE()),"") -> Bala Murugan | D21: 0.33472222 | E21: 0.62638889 | F21: 0.4 | G21: =ROUND(((E21-D21)*24)-F21,1) -> 6.6 | H21: Present
A22: 46280 | B22: R019 | C22: =IFERROR(VLOOKUP(B22,'Rider Performance Tracker'!$A$4:$B$23,2,FALSE()),"") -> Harish Chandra | D22: 0.39097222 | E22: 0.68263889 | F22: 0.6 | G22: =ROUND(((E22-D22)*24)-F22,1) -> 6.4 | H22: Present
A23: 46280 | B23: R020 | C23: =IFERROR(VLOOKUP(B23,'Rider Performance Tracker'!$A$4:$B$23,2,FALSE()),"") -> Dinesh Kumar | F23: 0 | G23: 0 | H23: Absent
A24: 46281 | B24: R001 | C24: =IFERROR(VLOOKUP(B24,'Rider Performance Tracker'!$A$4:$B$23,2,FALSE()),"") -> Rahul Verma | D24: 0.32152778 | E24: 0.61319444 | F24: 0.6 | G24: =ROUND(((E24-D24)*24)-F24,1) -> 6.4 | H24: Present
A25: 46281 | B25: R002 | C25: =IFERROR(VLOOKUP(B25,'Rider Performance Tracker'!$A$4:$B$23,2,FALSE()),"") -> Sandeep Yadav | D25: 0.36666667 | E25: 0.65833333 | F25: 0.4 | G25: =ROUND(((E25-D25)*24)-F25,1) -> 6.6 | H25: Present
A26: 46281 | B26: R003 | C26: =IFERROR(VLOOKUP(B26,'Rider Performance Tracker'!$A$4:$B$23,2,FALSE()),"") -> Kiran Kumar | D26: 0.35069444 | E26: 0.64236111 | F26: 0.5 | G26: =ROUND(((E26-D26)*24)-F26,1) -> 6.5 | H26: Present
A27: 46281 | B27: R004 | C27: =IFERROR(VLOOKUP(B27,'Rider Performance Tracker'!$A$4:$B$23,2,FALSE()),"") -> Manoj Das | D27: 0.29236111 | E27: 0.58402778 | F27: 0.8 | G27: =ROUND(((E27-D27)*24)-F27,1) -> 6.2 | H27: Present
A28: 46281 | B28: R005 | C28: =IFERROR(VLOOKUP(B28,'Rider Performance Tracker'!$A$4:$B$23,2,FALSE()),"") -> Vishal Chauhan | D28: 0.37361111 | E28: 0.66527778 | F28: 0.7 | G28: =ROUND(((E28-D28)*24)-F28,1) -> 6.3 | H28: Present
A29: 46281 | B29: R006 | C29: =IFERROR(VLOOKUP(B29,'Rider Performance Tracker'!$A$4:$B$23,2,FALSE()),"") -> Ajay Patil | D29: 0.36458333 | E29: 0.65625 | F29: 0.6 | G29: =ROUND(((E29-D29)*24)-F29,1) -> 6.4 | H29: Present
A30: 46281 | B30: R007 | C30: =IFERROR(VLOOKUP(B30,'Rider Performance Tracker'!$A$4:$B$23,2,FALSE()),"") -> Suraj Shetty | F30: 0 | G30: 0 | H30: Leave
A31: 46281 | B31: R008 | C31: =IFERROR(VLOOKUP(B31,'Rider Performance Tracker'!$A$4:$B$23,2,FALSE()),"") -> Rohit Bose | D31: 0.34166667 | E31: 0.63333333 | F31: 0.4 | G31: =ROUND(((E31-D31)*24)-F31,1) -> 6.6 | H31: Present
A32: 46281 | B32: R009 | C32: =IFERROR(VLOOKUP(B32,'Rider Performance Tracker'!$A$4:$B$23,2,FALSE()),"") -> Farhan Ali | D32: 0.54930556 | E32: 0.71597222 | F32: 0.9 | G32: =ROUND(((E32-D32)*24)-F32,1) -> 3.1 | H32: Half Day
A33: 46281 | B33: R010 | C33: =IFERROR(VLOOKUP(B33,'Rider Performance Tracker'!$A$4:$B$23,2,FALSE()),"") -> Gautam Joshi | D33: 0.32708333 | E33: 0.61875 | F33: 0.8 | G33: =ROUND(((E33-D33)*24)-F33,1) -> 6.2 | H33: Present
A34: 46281 | B34: R011 | C34: =IFERROR(VLOOKUP(B34,'Rider Performance Tracker'!$A$4:$B$23,2,FALSE()),"") -> Nikhil Rane | D34: 0.57083333 | E34: 0.7375 | F34: 0.5 | G34: =ROUND(((E34-D34)*24)-F34,1) -> 3.5 | H34: Half Day
A35: 46281 | B35: R012 | C35: =IFERROR(VLOOKUP(B35,'Rider Performance Tracker'!$A$4:$B$23,2,FALSE()),"") -> Prakash Naidu | D35: 0.3875 | E35: 0.67916667 | F35: 0.9 | G35: =ROUND(((E35-D35)*24)-F35,1) -> 6.1 | H35: Present
A36: 46281 | B36: R013 | C36: =IFERROR(VLOOKUP(B36,'Rider Performance Tracker'!$A$4:$B$23,2,FALSE()),"") -> Irfan Khan | D36: 0.61458333 | E36: 0.78125 | F36: 0.9 | G36: =ROUND(((E36-D36)*24)-F36,1) -> 3.1 | H36: Half Day
A37: 46281 | B37: R014 | C37: =IFERROR(VLOOKUP(B37,'Rider Performance Tracker'!$A$4:$B$23,2,FALSE()),"") -> Tarun Bhatia | D37: 0.35555556 | E37: 0.64722222 | F37: 0.5 | G37: =ROUND(((E37-D37)*24)-F37,1) -> 6.5 | H37: Present
A38: 46281 | B38: R015 | C38: =IFERROR(VLOOKUP(B38,'Rider Performance Tracker'!$A$4:$B$23,2,FALSE()),"") -> Yusuf Sheikh | F38: 0 | G38: 0 | H38: Leave
A39: 46281 | B39: R016 | C39: =IFERROR(VLOOKUP(B39,'Rider Performance Tracker'!$A$4:$B$23,2,FALSE()),"") -> Aditya Menon | D39: 0.32638889 | E39: 0.61805556 | F39: 0.6 | G39: =ROUND(((E39-D39)*24)-F39,1) -> 6.4 | H39: Present
A40: 46281 | B40: R017 | C40: =IFERROR(VLOOKUP(B40,'Rider Performance Tracker'!$A$4:$B$23,2,FALSE()),"") -> Sameer Qureshi | D40: 0.39097222 | E40: 0.68263889 | F40: 0.6 | G40: =ROUND(((E40-D40)*24)-F40,1) -> 6.4 | H40: Present
A41: 46281 | B41: R018 | C41: =IFERROR(VLOOKUP(B41,'Rider Performance Tracker'!$A$4:$B$23,2,FALSE()),"") -> Bala Murugan | F41: 0 | G41: 0 | H41: Leave
A42: 46281 | B42: R019 | C42: =IFERROR(VLOOKUP(B42,'Rider Performance Tracker'!$A$4:$B$23,2,FALSE()),"") -> Harish Chandra | D42: 0.29444444 | E42: 0.58611111 | F42: 0.5 | G42: =ROUND(((E42-D42)*24)-F42,1) -> 6.5 | H42: Present
A43: 46281 | B43: R020 | C43: =IFERROR(VLOOKUP(B43,'Rider Performance Tracker'!$A$4:$B$23,2,FALSE()),"") -> Dinesh Kumar | F43: 0 | G43: 0 | H43: Leave
A44: 46282 | B44: R001 | C44: =IFERROR(VLOOKUP(B44,'Rider Performance Tracker'!$A$4:$B$23,2,FALSE()),"") -> Rahul Verma | D44: 0.39305556 | E44: 0.68472222 | F44: 0.8 | G44: =ROUND(((E44-D44)*24)-F44,1) -> 6.2 | H44: Present
A45: 46282 | B45: R002 | C45: =IFERROR(VLOOKUP(B45,'Rider Performance Tracker'!$A$4:$B$23,2,FALSE()),"") -> Sandeep Yadav | D45: 0.50555556 | E45: 0.67222222 | F45: 1 | G45: =ROUND(((E45-D45)*24)-F45,1) -> 3 | H45: Half Day
A46: 46282 | B46: R003 | C46: =IFERROR(VLOOKUP(B46,'Rider Performance Tracker'!$A$4:$B$23,2,FALSE()),"") -> Kiran Kumar | D46: 0.35347222 | E46: 0.64513889 | F46: 0.8 | G46: =ROUND(((E46-D46)*24)-F46,1) -> 6.2 | H46: Present
A47: 46282 | B47: R004 | C47: =IFERROR(VLOOKUP(B47,'Rider Performance Tracker'!$A$4:$B$23,2,FALSE()),"") -> Manoj Das | D47: 0.40277778 | E47: 0.69444444 | F47: 0.7 | G47: =ROUND(((E47-D47)*24)-F47,1) -> 6.3 | H47: Present
A48: 46282 | B48: R005 | C48: =IFERROR(VLOOKUP(B48,'Rider Performance Tracker'!$A$4:$B$23,2,FALSE()),"") -> Vishal Chauhan | D48: 0.31041667 | E48: 0.60208333 | F48: 0.7 | G48: =ROUND(((E48-D48)*24)-F48,1) -> 6.3 | H48: Present
A49: 46282 | B49: R006 | C49: =IFERROR(VLOOKUP(B49,'Rider Performance Tracker'!$A$4:$B$23,2,FALSE()),"") -> Ajay Patil | D49: 0.52291667 | E49: 0.68958333 | F49: 0.4 | G49: =ROUND(((E49-D49)*24)-F49,1) -> 3.6 | H49: Half Day
A50: 46282 | B50: R007 | C50: =IFERROR(VLOOKUP(B50,'Rider Performance Tracker'!$A$4:$B$23,2,FALSE()),"") -> Suraj Shetty | D50: 0.37430556 | E50: 0.66597222 | F50: 0.8 | G50: =ROUND(((E50-D50)*24)-F50,1) -> 6.2 | H50: Present
A51: 46282 | B51: R008 | C51: =IFERROR(VLOOKUP(B51,'Rider Performance Tracker'!$A$4:$B$23,2,FALSE()),"") -> Rohit Bose | D51: 0.41458333 | E51: 0.70625 | F51: 0.5 | G51: =ROUND(((E51-D51)*24)-F51,1) -> 6.5 | H51: Present
A52: 46282 | B52: R009 | C52: =IFERROR(VLOOKUP(B52,'Rider Performance Tracker'!$A$4:$B$23,2,FALSE()),"") -> Farhan Ali | D52: 0.31944444 | E52: 0.61111111 | F52: 1 | G52: =ROUND(((E52-D52)*24)-F52,1) -> 6 | H52: Present
A53: 46282 | B53: R010 | C53: =IFERROR(VLOOKUP(B53,'Rider Performance Tracker'!$A$4:$B$23,2,FALSE()),"") -> Gautam Joshi | D53: 0.38819444 | E53: 0.67986111 | F53: 0.7 | G53: =ROUND(((E53-D53)*24)-F53,1) -> 6.3 | H53: Present
A54: 46282 | B54: R011 | C54: =IFERROR(VLOOKUP(B54,'Rider Performance Tracker'!$A$4:$B$23,2,FALSE()),"") -> Nikhil Rane | D54: 0.38194444 | E54: 0.67361111 | F54: 0.7 | G54: =ROUND(((E54-D54)*24)-F54,1) -> 6.3 | H54: Present
A55: 46282 | B55: R012 | C55: =IFERROR(VLOOKUP(B55,'Rider Performance Tracker'!$A$4:$B$23,2,FALSE()),"") -> Prakash Naidu | D55: 0.32083333 | E55: 0.6125 | F55: 0.7 | G55: =ROUND(((E55-D55)*24)-F55,1) -> 6.3 | H55: Present
... A60: 46282 | B60: R017 | C60: =IFERROR(VLOOKUP(B60,'Rider Performance Tracker'!$A$4:$B$23,2,FALSE()),"") -> Sameer Qureshi | D60: 0.39861111 | E60: 0.69027778 | F60: 0.5 | G60: =ROUND(((E60-D60)*24)-F60,1) -> 6.5 | H60: Present
A61: 46282 | B61: R018 | C61: =IFERROR(VLOOKUP(B61,'Rider Performance Tracker'!$A$4:$B$23,2,FALSE()),"") -> Bala Murugan | F61: 0 | G61: 0 | H61: Leave
A62: 46282 | B62: R019 | C62: =IFERROR(VLOOKUP(B62,'Rider Performance Tracker'!$A$4:$B$23,2,FALSE()),"") -> Harish Chandra | D62: 0.39236111 | E62: 0.68402778 | F62: 0.5 | G62: =ROUND(((E62-D62)*24)-F62,1) -> 6.5 | H62: Present
A63: 46282 | B63: R020 | C63: =IFERROR(VLOOKUP(B63,'Rider Performance Tracker'!$A$4:$B$23,2,FALSE()),"") -> Dinesh Kumar | D63: 0.29861111 | E63: 0.59027778 | F63: 0.6 | G63: =ROUND(((E63-D63)*24)-F63,1) -> 6.4 | H63: Present

Sheet Customer Complaints
A1: CUSTOMER COMPLAINTS
A2: Zone is pulled live via VLOOKUP from the Order ID.
A3: Complaint ID | B3: Order ID | C3: Zone | D3: Complaint Type | E3: Resolution Time (hrs) | F3: Status | G3: Responsible Team
A4: CMP2001 | B4: ORD1068 | C4: =VLOOKUP(B4,'Daily Order Tracker'!$B$4:$E$93,4,FALSE()) -> Sarjapur | D4: Wrong Order | E4: 12 | F4: Resolved | G4: Customer Support
A5: CMP2002 | B5: ORD1066 | C5: =VLOOKUP(B5,'Daily Order Tracker'!$B$4:$E$93,4,FALSE()) -> BTM Layout | D5: Wrong Order | E5: 12.3 | F5: Resolved | G5: Kitchen Ops
A6: CMP2003 | B6: ORD1029 | C6: =VLOOKUP(B6,'Daily Order Tracker'!$B$4:$E$93,4,FALSE()) -> Bellandur | D6: Missing Item | E6: 45.4 | F6: Resolved | G6: Logistics
A7: CMP2004 | B7: ORD1048 | C7: =VLOOKUP(B7,'Daily Order Tracker'!$B$4:$E$93,4,FALSE()) -> Bellandur | D7: Late Delivery | F7: In Progress | G7: Customer Support
A8: CMP2005 | B8: ORD1019 | C8: =VLOOKUP(B8,'Daily Order Tracker'!$B$4:$E$93,4,FALSE()) -> Bellandur | D8: Refund Issue | F8: Escalated | G8: Customer Support
A9: CMP2006 | B9: ORD1045 | C9: =VLOOKUP(B9,'Daily Order Tracker'!$B$4:$E$93,4,FALSE()) -> Marathahalli | D9: Late Delivery | F9: In Progress | G9: Logistics
A10: CMP2007 | B10: ORD1076 | C10: =VLOOKUP(B10,'Daily Order Tracker'!$B$4:$E$93,4,FALSE()) -> BTM Layout | D10: Rider Behaviour | F10: Escalated | G10: Logistics
A11: CMP2008 | B11: ORD1049 | C11: =VLOOKUP(B11,'Daily Order Tracker'!$B$4:$E$93,4,FALSE()) -> Sarjapur | D11: Wrong Order | E11: 24.1 | F11: Resolved | G11: Logistics
A12: CMP2009 | B12: ORD1057 | C12: =VLOOKUP(B12,'Daily Order Tracker'!$B$4:$E$93,4,FALSE()) -> BTM Layout | D12: Rider Behaviour | F12: Escalated | G12: Rider Ops
A13: CMP2010 | B13: ORD1009 | C13: =VLOOKUP(B13,'Daily Order Tracker'!$B$4:$E$93,4,FALSE()) -> Bellandur | D13: Missing Item | F13: In Progress | G13: Customer Support
A14: CMP2011 | B14: ORD1054 | C14: =VLOOKUP(B14,'Daily Order Tracker'!$B$4:$E$93,4,FALSE()) -> Electronic City | D14: Wrong Order | F14: Open | G14: Customer Support
A15: CMP2012 | B15: ORD1026 | C15: =VLOOKUP(B15,'Daily Order Tracker'!$B$4:$E$93,4,FALSE()) -> Marathahalli | D15: Refund Issue | E15: 28.9 | F15: Resolved | G15: Logistics
A16: CMP2013 | B16: ORD1036 | C16: =VLOOKUP(B16,'Daily Order Tracker'!$B$4:$E$93,4,FALSE()) -> JP Nagar | D16: Wrong Order | E16: 26 | F16: Resolved | G16: Logistics
A17: CMP2014 | B17: ORD1040 | C17: =VLOOKUP(B17,'Daily Order Tracker'!$B$4:$E$93,4,FALSE()) -> Koramangala | D17: Food Quality | F17: In Progress | G17: Customer Support
A18: CMP2015 | B18: ORD1007 | C18: =VLOOKUP(B18,'Daily Order Tracker'!$B$4:$E$93,4,FALSE()) -> JP Nagar | D18: Rider Behaviour | E18: 17.9 | F18: Resolved | G18: Kitchen Ops

Sheet Cancellation & Refund Tracker
A1: CANCELLATION & REFUND TRACKER
A2: Zone and Order Value pulled live via VLOOKUP from Daily Order Tracker.
A3: Order ID | B3: Zone | C3: Order Value (₹) | D3: Cancellation Reason | E3: Refund Amount (₹) | F3: Responsible Stage | G3: Recovery Analysis
A4: ORD1023 | B4: =VLOOKUP(A4,'Daily Order Tracker'!$B$4:$E$93,4,FALSE()) -> Indiranagar | C4: =VLOOKUP(A4,'Daily Order Tracker'!$B$4:$P$93,15,FALSE()) -> 542 | D4: Address unserviceable | E4: =C4*1 -> 542 | F4: Payment | G4: Refunded to Source
A5: ORD1024 | B5: =VLOOKUP(A5,'Daily Order Tracker'!$B$4:$E$93,4,FALSE()) -> Whitefield | C5: =VLOOKUP(A5,'Daily Order Tracker'!$B$4:$P$93,15,FALSE()) -> 348 | D5: Rider unavailable | E5: =C5*1 -> 348 | F5: Payment | G5: Under Review
A6: ORD1035 | B6: =VLOOKUP(A6,'Daily Order Tracker'!$B$4:$E$93,4,FALSE()) -> Marathahalli | C6: =VLOOKUP(A6,'Daily Order Tracker'!$B$4:$P$93,15,FALSE()) -> 147 | D6: Customer changed mind | E6: =C6*0.9 -> 132.3 | F6: Delivery | G6: Refunded to Wallet
A7: ORD1039 | B7: =VLOOKUP(A7,'Daily Order Tracker'!$B$4:$E$93,4,FALSE()) -> Sarjapur | C7: =VLOOKUP(A7,'Daily Order Tracker'!$B$4:$P$93,15,FALSE()) -> 469 | D7: Payment failed | E7: =C7*1 -> 469 | F7: Payment | G7: Under Review
A8: ORD1051 | B8: =VLOOKUP(A8,'Daily Order Tracker'!$B$4:$E$93,4,FALSE()) -> HSR Layout | C8: =VLOOKUP(A8,'Daily Order Tracker'!$B$4:$P$93,15,FALSE()) -> 376 | D8: Address unserviceable | E8: =C8*1 -> 376 | F8: Payment | G8: Refunded to Wallet
A9: ORD1064 | B9: =VLOOKUP(A9,'Daily Order Tracker'!$B$4:$E$93,4,FALSE()) -> Marathahalli | C9: =VLOOKUP(A9,'Daily Order Tracker'!$B$4:$P$93,15,FALSE()) -> 401 | D9: Kitchen closed item unavailable | E9: =C9*1 -> 401 | F9: Order Placement | G9: Non-recoverable
A10: ORD1071 | B10: =VLOOKUP(A10,'Daily Order Tracker'!$B$4:$E$93,4,FALSE()) -> Indiranagar | C10: =VLOOKUP(A10,'Daily Order Tracker'!$B$4:$P$93,15,FALSE()) -> 330 | D10: Rider unavailable | E10: =C10*1 -> 330 | F10: Rider Assignment | G10: Refunded to Wallet
A11: ORD1074 | B11: =VLOOKUP(A11,'Daily Order Tracker'!$B$4:$E$93,4,FALSE()) -> Marathahalli | C11: =VLOOKUP(A11,'Daily Order Tracker'!$B$4:$P$93,15,FALSE()) -> 574 | D11: Rider unavailable | E11: =C11*1 -> 574 | F11: Kitchen | G11: Refunded to Source
A12: ORD1075 | B12: =VLOOKUP(A12,'Daily Order Tracker'!$B$4:$E$93,4,FALSE()) -> JP Nagar | C12: =VLOOKUP(A12,'Daily Order Tracker'!$B$4:$P$93,15,FALSE()) -> 560 | D12: Address unserviceable | E12: =C12*1 -> 560 | F12: Payment | G12: Non-recoverable
A13: ORD1082 | B13: =VLOOKUP(A13,'Daily Order Tracker'!$B$4:$E$93,4,FALSE()) -> Whitefield | C13: =VLOOKUP(A13,'Daily Order Tracker'!$B$4:$P$93,15,FALSE()) -> 176 | D13: Address unserviceable | E13: =C13*1 -> 176 | F13: Order Placement | G13: Refunded to Wallet
